Workbook

Sheet Summary
A2: Scenario | B2: Description
A3: 1 | B3: Convertible preferred
A4: 2 | B4: Participating preferred
A5: 3 | B5: Participating preferred with cap
A6: 4 | B6: Convertible preferred with 2x liquidation preference
A7: 5 | B7: Convertible preferred with accruing dividends that convert
A8: 6 | B8: Convertible preferred with accruing dividends that don't convert

Sheet 1.a Capital Structure
A1: class_name | B1: type | C1: sharecount | D1: seniority | E1: liquidation_preference_per_share | F1: convertible | G1: conversion_ratio | H1: participating | I1: participation_cap_multiple
A2: Series A Preferred | B2: Preferred | C2: 100000 | D2: 6 | E2: 10 | F2: TRUE | G2: 1
A3: Series B Preferred | B3: Preferred | C3: 150000 | D3: 5 | E3: 25 | F3: TRUE | G3: 1
A4: Series C Preferred | B4: Preferred | C4: 200000 | D4: 4 | E4: 50 | F4: TRUE | G4: 1
A5: Series D Preferred | B5: Preferred | C5: 225000 | D5: 3 | E5: 100 | F5: TRUE | G5: 1
A6: Series E Preferred | B6: Preferred | C6: 250000 | D6: 2 | E6: 400 | F6: TRUE | G6: 1
A7: Series F Preferred | B7: Preferred | C7: 300000 | D7: 1 | E7: 500 | F7: TRUE | G7: 1
A8: Common | B8: Common | C8: 800000

Sheet 1.b  OPM
B5: Inputs & Assumptions | G5: Series A Preferred | H5: Series B Preferred | I5: Series C Preferred | J5: Series D Preferred | K5: Series E Preferred | L5: Series F Preferred | M5: Common
B7: Equity Value | C7: 750000000 | G7: ='1.a Capital Structure'!D2 -> 6 | H7: ='1.a Capital Structure'!D3 -> 5 | I7: ='1.a Capital Structure'!D4 -> 4 | J7: ='1.a Capital Structure'!D5 -> 3 | K7: ='1.a Capital Structure'!D6 -> 2 | L7: ='1.a Capital Structure'!D7 -> 1 | N7: Priority
B8: T | C8: 2 | G8: ='1.a Capital Structure'!C2 -> 100000 | H8: ='1.a Capital Structure'!C3 -> 150000 | I8: ='1.a Capital Structure'!C4 -> 200000 | J8: ='1.a Capital Structure'!C5 -> 225000 | K8: ='1.a Capital Structure'!C6 -> 250000 | L8: ='1.a Capital Structure'!C7 -> 300000 | M8: ='1.a Capital Structure'!C8 -> 800000 | N8: Sharecount
B9: Volatility | C9: 0.45 | G9: ='1.a Capital Structure'!E2 -> 10 | H9: ='1.a Capital Structure'!E3 -> 25 | I9: ='1.a Capital Structure'!E4 -> 50 | J9: ='1.a Capital Structure'!E5 -> 100 | K9: ='1.a Capital Structure'!E6 -> 400 | L9: ='1.a Capital Structure'!E7 -> 500 | N9: Liquidation Preference (per share)
B10: Risk-free Rate | C10: 0.04 | G10: =G8*G9 -> 1000000 | H10: =H8*H9 -> 3750000 | I10: =I8*I9 -> 10000000 | J10: =J8*J9 -> 22500000 | K10: =K8*K9 -> 100000000 | L10: =L8*L9 -> 150000000 | N10: Liquidation Preference (total)
B15: Breakpoints
B16: From | C16: To | G16: =G5 -> Series A Preferred | H16: =H5 -> Series B Preferred | I16: =I5 -> Series C Preferred | J16: =J5 -> Series D Preferred | K16: =K5 -> Series E Preferred | L16: =L5 -> Series F Preferred | M16: =M5 -> Common
B18: 0 | C18: =B18+SUM(G18:L18) -> 150000000 | L18: =L10 -> 150000000
B19: =C18 -> 150000000 | C19: =B19+SUM(G19:L19) -> 250000000 | K19: =K10 -> 100000000
B20: =C19 -> 250000000 | C20: =B20+SUM(G20:L20) -> 272500000 | J20: =J10 -> 22500000
B21: =C20 -> 272500000 | C21: =B21+SUM(G21:L21) -> 282500000 | I21: =I10 -> 10000000
B22: =C21 -> 282500000 | C22: =B22+SUM(G22:L22) -> 286250000 | H22: =H10 -> 3750000
B23: =C22 -> 286250000 | C23: =B23+SUM(G23:L23) -> 287250000 | G23: =G10 -> 1000000
B24: =C23 -> 287250000 | C24: =B24+(E24-E23)*SUM(G24:M24) -> 295250000 | E24: =G9 -> 10 | M24: =M$8 -> 800000
B25: =C24 -> 295250000 | C25: =B25+(E25-E24)*SUM(G25:M25) -> 308750000 | E25: =H9 -> 25 | G25: =G$8 -> 100000 | M25: =M$8 -> 800000
B26: =C25 -> 308750000 | C26: =B26+(E26-E25)*SUM(G26:M26) -> 335000000 | E26: =I9 -> 50 | G26: =G$8 -> 100000 | H26: =H$8 -> 150000 | M26: =M$8 -> 800000
B27: =C26 -> 335000000 | C27: =B27+(E27-E26)*SUM(G27:M27) -> 397500000 | E27: =J9 -> 100 | G27: =G$8 -> 100000 | H27: =H$8 -> 150000 | I27: =I$8 -> 200000 | M27: =M$8 -> 800000
B28: =C27 -> 397500000 | C28: =B28+(E28-E27)*SUM(G28:M28) -> 840000000 | E28: =K9 -> 400 | G28: =G$8 -> 100000 | H28: =H$8 -> 150000 | I28: =I$8 -> 200000 | J28: =J$8 -> 225000 | M28: =M$8 -> 800000
B29: =C28 -> 840000000 | C29: =B29+(E29-E28)*SUM(G29:M29) -> 1012500000 | E29: =L9 -> 500 | G29: =G$8 -> 100000 | H29: =H$8 -> 150000 | I29: =I$8 -> 200000 | J29: =J$8 -> 225000 | K29: =K$8 -> 250000 | M29: =M$8 -> 800000
B30: =C29 -> 1012500000 | C30: and above | G30: =G$8 -> 100000 | H30: =H$8 -> 150000 | I30: =I$8 -> 200000 | J30: =J$8 -> 225000 | K30: =K$8 -> 250000 | L30: =L$8 -> 300000 | M30: =M$8 -> 800000
B35: Breakpoints | E35: Incremental
B36: =B16 -> From | C36: =C16 -> To | E36: Distribution
B38: =B18 -> 0 | C38: =C18 -> 150000000 | E38: =C38-B38 -> 150000000 | G38: Breakpoint 1 - Series F receives liquidation preference
B39: =B19 -> 150000000 | C39: =C19 -> 250000000 | E39: =C39-B39 -> 100000000 | G39: Breakpoint 2 - Series E receives liquidation preference
B40: =B20 -> 250000000 | C40: =C20 -> 272500000 | E40: =C40-B40 -> 22500000 | G40: Breakpoint 3 - Series D receives liquidation preference
B41: =B21 -> 272500000 | C41: =C21 -> 282500000 | E41: =C41-B41 -> 10000000 | G41: Breakpoint 4 - Series C receives liquidation preference
B42: =B22 -> 282500000 | C42: =C22 -> 286250000 | E42: =C42-B42 -> 3750000 | G42: Breakpoint 5 - Series B receives liquidation preference
B43: =B23 -> 286250000 | C43: =C23 -> 287250000 | E43: =C43-B43 -> 1000000 | G43: Breakpoint 6 - Series A receives liquidation preference
B44: =B24 -> 287250000 | C44: =C24 -> 295250000 | E44: =C44-B44 -> 8000000 | G44: Breakpoint 7 - Common recieves distributions until Series A converts
B45: =B25 -> 295250000 | C45: =C25 -> 308750000 | E45: =C45-B45 -> 13500000 | G45: Breakpoint 8 - Series A, Common receive distributions until Series B converts
B46: =B26 -> 308750000 | C46: =C26 -> 335000000 | E46: =C46-B46 -> 26250000 | G46: Breakpoint 9 - Series A, Series B, Common receive disturbtions until Series C converts
B47: =B27 -> 335000000 | C47: =C27 -> 397500000 | E47: =C47-B47 -> 62500000 | G47: Breakpoint 10 - Series A, Series B, Series C, Common receive distributions until Series D converts
B48: =B28 -> 397500000 | C48: =C28 -> 840000000 | E48: =C48-B48 -> 442500000 | G48: Breakpoint 11 - Series A, Series B, Series C, Series D, Common receive distributions until Series E converts
B49: =B29 -> 840000000 | C49: =C29 -> 1012500000 | E49: =C49-B49 -> 172500000 | G49: Breakpoint 12 - Series A, Series B, Series C, Series D, Series E, Common receive distributions until Series E converts
B50: =B30 -> 1012500000 | C50: =C30 -> and above | G50: Breakpoint 13 - All shares receive distributions pro rata
B55: Breakpoints | E55: Total
B56: =B36 -> From | C56: =C36 -> To | E56: Allocation | G56: =G16 -> Series A Preferred | H56: =H16 -> Series B Preferred | I56: =I16 -> Series C Preferred | J56: =J16 -> Series D Preferred | K56: =K16 -> Series E Preferred | L56: =L16 -> Series F Preferred | M56: =M16 -> Common
B58: =B38 -> 0 | C58: =C38 -> 150000000 | E58: =SUM(G58:M58) -> 1 | G58: =G18/SUM($G18:$M18) -> 0 | H58: =H18/SUM($G18:$M18) -> 0 | I58: =I18/SUM($G18:$M18) -> 0 | J58: =J18/SUM($G18:$M18) -> 0 | K58: =K18/SUM($G18:$M18) -> 0 | L58: =L18/SUM($G18:$M18) -> 1 | M58: =M18/SUM($G18:$M18) -> 0
B59: =B39 -> 150000000 | C59: =C39 -> 250000000 | E59: =SUM(G59:M59) -> 1 | G59: =G19/SUM($G19:$M19) -> 0 | H59: =H19/SUM($G19:$M19) -> 0 | I59: =I19/SUM($G19:$M19) -> 0 | J59: =J19/SUM($G19:$M19) -> 0 | K59: =K19/SUM($G19:$M19) -> 1 | L59: =L19/SUM($G19:$M19) -> 0 | M59: =M19/SUM($G19:$M19) -> 0
B60: =B40 -> 250000000 | C60: =C40 -> 272500000 | E60: =SUM(G60:M60) -> 1 | G60: =G20/SUM($G20:$M20) -> 0 | H60: =H20/SUM($G20:$M20) -> 0 | I60: =I20/SUM($G20:$M20) -> 0 | J60: =J20/SUM($G20:$M20) -> 1 | K60: =K20/SUM($G20:$M20) -> 0 | L60: =L20/SUM($G20:$M20) -> 0 | M60: =M20/SUM($G20:$M20) -> 0
B61: =B41 -> 272500000 | C61: =C41 -> 282500000 | E61: =SUM(G61:M61) -> 1 | G61: =G21/SUM($G21:$M21) -> 0 | H61: =H21/SUM($G21:$M21) -> 0 | I61: =I21/SUM($G21:$M21) -> 1 | J61: =J21/SUM($G21:$M21) -> 0 | K61: =K21/SUM($G21:$M21) -> 0 | L61: =L21/SUM($G21:$M21) -> 0 | M61: =M21/SUM($G21:$M21) -> 0
B62: =B42 -> 282500000 | C62: =C42 -> 286250000 | E62: =SUM(G62:M62) -> 1 | G62: =G22/SUM($G22:$M22) -> 0 | H62: =H22/SUM($G22:$M22) -> 1 | I62: =I22/SUM($G22:$M22) -> 0 | J62: =J22/SUM($G22:$M22) -> 0 | K62: =K22/SUM($G22:$M22) -> 0 | L62: =L22/SUM($G22:$M22) -> 0 | M62: =M22/SUM($G22:$M22) -> 0
B63: =B43 -> 286250000 | C63: =C43 -> 287250000 | E63: =SUM(G63:M63) -> 1 | G63: =G23/SUM($G23:$M23) -> 1 | H63: =H23/SUM($G23:$M23) -> 0 | I63: =I23/SUM($G23:$M23) -> 0 | J63: =J23/SUM($G23:$M23) -> 0 | K63: =K23/SUM($G23:$M23) -> 0 | L63: =L23/SUM($G23:$M23) -> 0 | M63: =M23/SUM($G23:$M23) -> 0
B64: =B44 -> 287250000 | C64: =C44 -> 295250000 | E64: =SUM(G64:M64) -> 1 | G64: =G24/SUM($G24:$M24) -> 0 | H64: =H24/SUM($G24:$M24) -> 0 | I64: =I24/SUM($G24:$M24) -> 0 | J64: =J24/SUM($G24:$M24) -> 0 | K64: =K24/SUM($G24:$M24) -> 0 | L64: =L24/SUM($G24:$M24) -> 0 | M64: =M24/SUM($G24:$M24) -> 1
B65: =B45 -> 295250000 | C65: =C45 -> 308750000 | E65: =SUM(G65:M65) -> 1 | G65: =G25/SUM($G25:$M25) -> 0.11111111 | H65: =H25/SUM($G25:$M25) -> 0 | I65: =I25/SUM($G25:$M25) -> 0 | J65: =J25/SUM($G25:$M25) -> 0 | K65: =K25/SUM($G25:$M25) -> 0 | L65: =L25/SUM($G25:$M25) -> 0 | M65: =M25/SUM($G25:$M25) -> 0.88888889
B66: =B46 -> 308750000 | C66: =C46 -> 335000000 | E66: =SUM(G66:M66) -> 1 | G66: =G26/SUM($G26:$M26) -> 0.095238095 | H66: =H26/SUM($G26:$M26) -> 0.14285714 | I66: =I26/SUM($G26:$M26) -> 0 | J66: =J26/SUM($G26:$M26) -> 0 | K66: =K26/SUM($G26:$M26) -> 0 | L66: =L26/SUM($G26:$M26) -> 0 | M66: =M26/SUM($G26:$M26) -> 0.76190476
B67: =B47 -> 335000000 | C67: =C47 -> 397500000 | E67: =SUM(G67:M67) -> 1 | G67: =G27/SUM($G27:$M27) -> 0.08 | H67: =H27/SUM($G27:$M27) -> 0.12 | I67: =I27/SUM($G27:$M27) -> 0.16 | J67: =J27/SUM($G27:$M27) -> 0 | K67: =K27/SUM($G27:$M27) -> 0 | L67: =L27/SUM($G27:$M27) -> 0 | M67: =M27/SUM($G27:$M27) -> 0.64
B68: =B48 -> 397500000 | C68: =C48 -> 840000000 | E68: =SUM(G68:M68) -> 1 | G68: =G28/SUM($G28:$M28) -> 0.06779661 | H68: =H28/SUM($G28:$M28) -> 0.10169492 | I68: =I28/SUM($G28:$M28) -> 0.13559322 | J68: =J28/SUM($G28:$M28) -> 0.15254237 | K68: =K28/SUM($G28:$M28) -> 0 | L68: =L28/SUM($G28:$M28) -> 0 | M68: =M28/SUM($G28:$M28) -> 0.54237288
B69: =B49 -> 840000000 | C69: =C49 -> 1012500000 | E69: =SUM(G69:M69) -> 1 | G69: =G29/SUM($G29:$M29) -> 0.057971014 | H69: =H29/SUM($G29:$M29) -> 0.086956522 | I69: =I29/SUM($G29:$M29) -> 0.11594203 | J69: =J29/SUM($G29:$M29) -> 0.13043478 | K69: =K29/SUM($G29:$M29) -> 0.14492754 | L69: =L29/SUM($G29:$M29) -> 0 | M69: =M29/SUM($G29:$M29) -> 0.46376812
B70: =B50 -> 1012500000 | C70: =C50 -> and above | E70: =SUM(G70:M70) -> 1 | G70: =G30/SUM($G30:$M30) -> 0.049382716 | H70: =H30/SUM($G30:$M30) -> 0.074074074 | I70: =I30/SUM($G30:$M30) -> 0.098765432 | J70: =J30/SUM($G30:$M30) -> 0.11111111 | K70: =K30/SUM($G30:$M30) -> 0.12345679 | L70: =L30/SUM($G30:$M30) -> 0.14814815 | M70: =M30/SUM($G30:$M30) -> 0.39506173
B75: =B55 -> Breakpoints | C75: =C55 -> 0 | E75: Option Value | O75: Call | V75: Incremental
B76: =B56 -> From | C76: =C56 -> To | G76: =G5 -> Series A Preferred | H76: =H5 -> Series B Preferred | I76: =I5 -> Series C Preferred | J76: =J5 -> Series D Preferred | K76: =K5 -> Series E Preferred | L76: =L5 -> Series F Preferred | M76: =M5 -> Common | O76: Option | Q76: N(d1) | R76: N(d2) | S76: d1 | T76: d2 | V76: N(d1)
B78: =B58 -> 0 | C78: =C58 -> 150000000 | E78: =O78-O79 -> 1.3822607e+08 | G78: =$E78*G58 -> 0 | H78: =$E78*H58 -> 0 | I78: =$E78*I58 -> 0 | J78: =$E78*J58 -> 0 | K78: =$E78*K58 -> 0 | L78: =$E78*L58 -> 1.3822607e+08 | M78: =$E78*M58 -> 0 | O78: =C7 -> 750000000 | Q78: 1 | V78: =Q78-Q79 -> 0.0014750334
B79: =B59 -> 150000000 | C79: =C59 -> 250000000 | E79: =O79-O80 -> 89367221 | G79: =$E79*G59 -> 0 | H79: =$E79*H59 -> 0 | I79: =$E79*I59 -> 0 | J79: =$E79*J59 -> 0 | K79: =$E79*K59 -> 89367221 | L79: =$E79*L59 -> 0 | M79: =$E79*M59 -> 0 | O79: =$C$7*Q79-B79*EXP(-$C$10*$C$8)*R79 -> 6.1177393e+08 | Q79: =NORMSDIST(S79) -> 0.99852497 | R79: =NORMSDIST(T79) -> 0.99026734 | S79: =(LN($C$7/B79)+($C$10+$C$9*$C$9/2)*$C$8)/($C$9*SQRT($C$8)) -> 2.9728936 | T79: =S79-$C$9*SQRT($C$8) -> 2.3364975 | V79: =Q79-Q80 -> 0.01352049
B80: =B60 -> 250000000 | C80: =C60 -> 272500000 | E80: =O80-O81 -> 19283083 | G80: =$E80*G60 -> 0 | H80: =$E80*H60 -> 0 | I80: =$E80*I60 -> 0 | J80: =$E80*J60 -> 19283083 | K80: =$E80*K60 -> 0 | L80: =$E80*L60 -> 0 | M80: =$E80*M60 -> 0 | O80: =$C$7*Q80-B80*EXP(-$C$10*$C$8)*R80 -> 5.2240671e+08 | Q80: =NORMSDIST(S80) -> 0.98500448 | R80: =NORMSDIST(T80) -> 0.9374621 | S80: =(LN($C$7/B80)+($C$10+$C$9*$C$9/2)*$C$8)/($C$9*SQRT($C$8)) -> 2.1702086 | T80: =S80-$C$9*SQRT($C$8) -> 1.5338125 | V80: =Q80-Q81 -> 0.0059403087
B81: =B61 -> 272500000 | C81: =C61 -> 282500000 | E81: =O81-O82 -> 8442953 | G81: =$E81*G61 -> 0 | H81: =$E81*H61 -> 0 | I81: =$E81*I61 -> 8442953 | J81: =$E81*J61 -> 0 | K81: =$E81*K61 -> 0 | L81: =$E81*L61 -> 0 | M81: =$E81*M61 -> 0 | O81: =$C$7*Q81-B81*EXP(-$C$10*$C$8)*R81 -> 5.0312363e+08 | Q81: =NORMSDIST(S81) -> 0.97906417 | R81: =NORMSDIST(T81) -> 0.9190031 | S81: =(LN($C$7/B81)+($C$10+$C$9*$C$9/2)*$C$8)/($C$9*SQRT($C$8)) -> 2.0347934 | T81: =S81-$C$9*SQRT($C$8) -> 1.3983973 | V81: =Q81-Q82 -> 0.0030193785
B82: =B62 -> 282500000 | C82: =C62 -> 286250000 | E82: =O82-O83 -> 3144819.1 | G82: =$E82*G62 -> 0 | H82: =$E82*H62 -> 3144819.1 | I82: =$E82*I62 -> 0 | J82: =$E82*J62 -> 0 | K82: =$E82*K62 -> 0 | L82: =$E82*L62 -> 0 | M82: =$E82*M62 -> 0 | O82: =$C$7*Q82-B82*EXP(-$C$10*$C$8)*R82 -> 4.9468067e+08 | Q82: =NORMSDIST(S82) -> 0.97604479 | R82: =NORMSDIST(T82) -> 0.91016406 | S82: =(LN($C$7/B82)+($C$10+$C$9*$C$9/2)*$C$8)/($C$9*SQRT($C$8)) -> 1.9781621 | T82: =S82-$C$9*SQRT($C$8) -> 1.341766 | V82: =Q82-Q83 -> 0.001192626
B83: =B63 -> 286250000 | C83: =C63 -> 287250000 | E83: =O83-O84 -> 836619.07 | G83: =$E83*G63 -> 836619.07 | H83: =$E83*H63 -> 0 | I83: =$E83*I63 -> 0 | J83: =$E83*J63 -> 0 | K83: =$E83*K63 -> 0 | L83: =$E83*L63 -> 0 | M83: =$E83*M63 -> 0 | O83: =$C$7*Q83-B83*EXP(-$C$10*$C$8)*R83 -> 4.9153585e+08 | Q83: =NORMSDIST(S83) -> 0.97485216 | R83: =NORMSDIST(T83) -> 0.90675676 | S83: =(LN($C$7/B83)+($C$10+$C$9*$C$9/2)*$C$8)/($C$9*SQRT($C$8)) -> 1.9574407 | T83: =S83-$C$9*SQRT($C$8) -> 1.3210446 | V83: =Q83-Q84 -> 0.00032358839
B84: =B64 -> 287250000 | C84: =C64 -> 295250000 | E84: =O84-O85 -> 6662166.7 | G84: =$E84*G64 -> 0 | H84: =$E84*H64 -> 0 | I84: =$E84*I64 -> 0 | J84: =$E84*J64 -> 0 | K84: =$E84*K64 -> 0 | L84: =$E84*L64 -> 0 | M84: =$E84*M64 -> 6662166.7 | O84: =$C$7*Q84-B84*EXP(-$C$10*$C$8)*R84 -> 4.9069923e+08 | Q84: =NORMSDIST(S84) -> 0.97452857 | R84: =NORMSDIST(T84) -> 0.90583992 | S84: =(LN($C$7/B84)+($C$10+$C$9*$C$9/2)*$C$8)/($C$9*SQRT($C$8)) -> 1.9519609 | T84: =S84-$C$9*SQRT($C$8) -> 1.3155648 | V84: =Q84-Q85 -> 0.002672739
B85: =B65 -> 295250000 | C85: =C65 -> 308750000 | E85: =O85-O86 -> 11115063 | G85: =$E85*G65 -> 1235007 | H85: =$E85*H65 -> 0 | I85: =$E85*I65 -> 0 | J85: =$E85*J65 -> 0 | K85: =$E85*K65 -> 0 | L85: =$E85*L65 -> 0 | M85: =$E85*M65 -> 9880056.3 | O85: =$C$7*Q85-B85*EXP(-$C$10*$C$8)*R85 -> 4.8403707e+08 | Q85: =NORMSDIST(S85) -> 0.97185584 | R85: =NORMSDIST(T85) -> 0.89838458 | S85: =(LN($C$7/B85)+($C$10+$C$9*$C$9/2)*$C$8)/($C$9*SQRT($C$8)) -> 1.9087967 | T85: =S85-$C$9*SQRT($C$8) -> 1.2724005 | V85: =Q85-Q86 -> 0.004847084
B86: =B66 -> 308750000 | C86: =C66 -> 335000000 | E86: =O86-O87 -> 21132620 | G86: =$E86*G66 -> 2012630.5 | H86: =$E86*H66 -> 3018945.7 | I86: =$E86*I66 -> 0 | J86: =$E86*J66 -> 0 | K86: =$E86*K66 -> 0 | L86: =$E86*L66 -> 0 | M86: =$E86*M66 -> 16101044 | O86: =$C$7*Q86-B86*EXP(-$C$10*$C$8)*R86 -> 4.72922e+08 | Q86: =NORMSDIST(S86) -> 0.96700875 | R86: =NORMSDIST(T86) -> 0.8853466 | S86: =(LN($C$7/B86)+($C$10+$C$9*$C$9/2)*$C$8)/($C$9*SQRT($C$8)) -> 1.8385426 | T86: =S86-$C$9*SQRT($C$8) -> 1.2021465 | V86: =Q86-Q87 -> 0.010611864
B87: =B67 -> 335000000 | C87: =C67 -> 397500000 | E87: =O87-O88 -> 47572913 | G87: =$E87*G67 -> 3805833.1 | H87: =$E87*H67 -> 5708749.6 | I87: =$E87*I67 -> 7611666.1 | J87: =$E87*J67 -> 0 | K87: =$E87*K67 -> 0 | L87: =$E87*L67 -> 0 | M87: =$E87*M67 -> 30446664 | O87: =$C$7*Q87-B87*EXP(-$C$10*$C$8)*R87 -> 4.5178939e+08 | Q87: =NORMSDIST(S87) -> 0.95639689 | R87: =NORMSDIST(T87) -> 0.8585722 | S87: =(LN($C$7/B87)+($C$10+$C$9*$C$9/2)*$C$8)/($C$9*SQRT($C$8)) -> 1.7103227 | T87: =S87-$C$9*SQRT($C$8) -> 1.0739266 | V87: =Q87-Q88 -> 0.031115679
B88: =B68 -> 397500000 | C88: =C68 -> 840000000 | E88: =O88-O89 -> 2.2625105e+08 | G88: =$E88*G68 -> 15339054 | H88: =$E88*H68 -> 23008582 | I88: =$E88*I68 -> 30678109 | J88: =$E88*J68 -> 34512872 | K88: =$E88*K68 -> 0 | L88: =$E88*L68 -> 0 | M88: =$E88*M68 -> 1.2271244e+08 | O88: =$C$7*Q88-B88*EXP(-$C$10*$C$8)*R88 -> 4.0421647e+08 | Q88: =NORMSDIST(S88) -> 0.92528121 | R88: =NORMSDIST(T88) -> 0.78962616 | S88: =(LN($C$7/B88)+($C$10+$C$9*$C$9/2)*$C$8)/($C$9*SQRT($C$8)) -> 1.4415209 | T88: =S88-$C$9*SQRT($C$8) -> 0.80512478 | V88: =Q88-Q89 -> 0.3204674
B89: =B69 -> 840000000 | C89: =C69 -> 1012500000 | E89: =O89-O90 -> 48014034 | G89: =$E89*G69 -> 2783422.2 | H89: =$E89*H69 -> 4175133.4 | I89: =$E89*I69 -> 5566844.5 | J89: =$E89*J69 -> 6262700.1 | K89: =$E89*K69 -> 6958555.6 | L89: =$E89*L69 -> 0 | M89: =$E89*M69 -> 22267378 | O89: =$C$7*Q89-B89*EXP(-$C$10*$C$8)*R89 -> 1.7796542e+08 | Q89: =NORMSDIST(S89) -> 0.6048138 | R89: =NORMSDIST(T89) -> 0.35547928 | S89: =(LN($C$7/B89)+($C$10+$C$9*$C$9/2)*$C$8)/($C$9*SQRT($C$8)) -> 0.26582708 | T89: =S89-$C$9*SQRT($C$8) -> -0.37056903 | V89: =Q89-Q90 -> 0.11584832
B90: =B70 -> 1012500000 | C90: =C70 -> and above | E90: =O90-O91 -> 1.2995139e+08 | G90: =$E90*G70 -> 6417352.4 | H90: =$E90*H70 -> 9626028.5 | I90: =$E90*I70 -> 12834705 | J90: =$E90*J70 -> 14439043 | K90: =$E90*K70 -> 16043381 | L90: =$E90*L70 -> 19252057 | M90: =$E90*M70 -> 51338819 | O90: =$C$7*Q90-B90*EXP(-$C$10*$C$8)*R90 -> 1.2995139e+08 | Q90: =NORMSDIST(S90) -> 0.48896549 | R90: =NORMSDIST(T90) -> 0.25332626 | S90: =(LN($C$7/B90)+($C$10+$C$9*$C$9/2)*$C$8)/($C$9*SQRT($C$8)) -> -0.027662948 | T90: =S90-$C$9*SQRT($C$8) -> -0.66405905 | V90: =Q90-Q91 -> 0.48896549
E93: Fair Value (per class) | G93: =SUM(G78:G90) -> 32429919 | H93: =SUM(H78:H90) -> 48682258 | I93: =SUM(I78:I90) -> 65134277 | J93: =SUM(J78:J90) -> 74497698 | K93: =SUM(K78:K90) -> 1.1236916e+08 | L93: =SUM(L78:L90) -> 1.5747813e+08 | M93: =SUM(M78:M90) -> 2.5940856e+08
E95: Fair Value (per share) | G95: =G93/G8 -> 324.29919 | H95: =H93/H8 -> 324.54839 | I95: =I93/I8 -> 325.67139 | J95: =J93/J8 -> 331.10088 | K95: =K93/K8 -> 449.47663 | L95: =L93/L8 -> 524.92709 | M95: =M93/M8 -> 324.2607
E97: Series Specific Volatility | G97: =$C$9*SUMPRODUCT(G58:G70,$V$78:$V$90)*($C$7/G93) -> 0.5926918 | H97: =$C$9*SUMPRODUCT(H58:H70,$V$78:$V$90)*($C$7/H93) -> 0.59153925 | I97: =$C$9*SUMPRODUCT(I58:I70,$V$78:$V$90)*($C$7/I93) -> 0.58643146 | J97: =$C$9*SUMPRODUCT(J58:J70,$V$78:$V$90)*($C$7/J93) -> 0.56296429 | K97: =$C$9*SUMPRODUCT(K58:K70,$V$78:$V$90)*($C$7/K93) -> 0.27234538 | L97: =$C$9*SUMPRODUCT(L58:L70,$V$78:$V$90)*($C$7/L93) -> 0.15840992 | M97: =$C$9*SUMPRODUCT(M58:M70,$V$78:$V$90)*($C$7/M93) -> 0.59287146

Sheet 1.c  OPM (backsolve)
B5: Inputs & Assumptions | G5: Series A Preferred | H5: Series B Preferred | I5: Series C Preferred | J5: Series D Preferred | K5: Series E Preferred | L5: Series F Preferred | M5: Common
B7: Equity Value | C7: 6.3922036e+08 | G7: ='1.a Capital Structure'!D2 -> 6 | H7: ='1.a Capital Structure'!D3 -> 5 | I7: ='1.a Capital Structure'!D4 -> 4 | J7: ='1.a Capital Structure'!D5 -> 3 | K7: ='1.a Capital Structure'!D6 -> 2 | L7: ='1.a Capital Structure'!D7 -> 1 | N7: Priority
B8: T | C8: 2 | G8: ='1.a Capital Structure'!C2 -> 100000 | H8: ='1.a Capital Structure'!C3 -> 150000 | I8: ='1.a Capital Structure'!C4 -> 200000 | J8: ='1.a Capital Structure'!C5 -> 225000 | K8: ='1.a Capital Structure'!C6 -> 250000 | L8: ='1.a Capital Structure'!C7 -> 300000 | M8: ='1.a Capital Structure'!C8 -> 800000 | N8: Sharecount
B9: Volatility | C9: 0.45 | G9: ='1.a Capital Structure'!E2 -> 10 | H9: ='1.a Capital Structure'!E3 -> 25 | I9: ='1.a Capital Structure'!E4 -> 50 | J9: ='1.a Capital Structure'!E5 -> 100 | K9: ='1.a Capital Structure'!E6 -> 400 | L9: ='1.a Capital Structure'!E7 -> 500 | N9: Liquidation Preference (per share)
B10: Risk-free Rate | C10: 0.04 | G10: =G8*G9 -> 1000000 | H10: =H8*H9 -> 3750000 | I10: =I8*I9 -> 10000000 | J10: =J8*J9 -> 22500000 | K10: =K8*K9 -> 100000000 | L10: =L8*L9 -> 150000000 | N10: Liquidation Preference (total)
B15: Breakpoints
B16: From | C16: To | G16: =G5 -> Series A Preferred | H16: =H5 -> Series B Preferred | I16: =I5 -> Series C Preferred | J16: =J5 -> Series D Preferred | K16: =K5 -> Series E Preferred | L16: =L5 -> Series F Preferred | M16: =M5 -> Common
B18: 0 | C18: =B18+SUM(G18:L18) -> 150000000 | L18: =L10 -> 150000000
B19: =C18 -> 150000000 | C19: =B19+SUM(G19:L19) -> 250000000 | K19: =K10 -> 100000000
B20: =C19 -> 250000000 | C20: =B20+SUM(G20:L20) -> 272500000 | J20: =J10 -> 22500000
B21: =C20 -> 272500000 | C21: =B21+SUM(G21:L21) -> 282500000 | I21: =I10 -> 10000000
B22: =C21 -> 282500000 | C22: =B22+SUM(G22:L22) -> 286250000 | H22: =H10 -> 3750000
B23: =C22 -> 286250000 | C23: =B23+SUM(G23:L23) -> 287250000 | G23: =G10 -> 1000000
B24: =C23 -> 287250000 | C24: =B24+(E24-E23)*SUM(G24:M24) -> 295250000 | E24: =G9 -> 10 | M24: =M$8 -> 800000
B25: =C24 -> 295250000 | C25: =B25+(E25-E24)*SUM(G25:M25) -> 308750000 | E25: =H9 -> 25 | G25: =G$8 -> 100000 | M25: =M$8 -> 800000
B26: =C25 -> 308750000 | C26: =B26+(E26-E25)*SUM(G26:M26) -> 335000000 | E26: =I9 -> 50 | G26: =G$8 -> 100000 | H26: =H$8 -> 150000 | M26: =M$8 -> 800000
B27: =C26 -> 335000000 | C27: =B27+(E27-E26)*SUM(G27:M27) -> 397500000 | E27: =J9 -> 100 | G27: =G$8 -> 100000 | H27: =H$8 -> 150000 | I27: =I$8 -> 200000 | M27: =M$8 -> 800000
B28: =C27 -> 397500000 | C28: =B28+(E28-E27)*SUM(G28:M28) -> 840000000 | E28: =K9 -> 400 | G28: =G$8 -> 100000 | H28: =H$8 -> 150000 | I28: =I$8 -> 200000 | J28: =J$8 -> 225000 | M28: =M$8 -> 800000
B29: =C28 -> 840000000 | C29: =B29+(E29-E28)*SUM(G29:M29) -> 1012500000 | E29: =L9 -> 500 | G29: =G$8 -> 100000 | H29: =H$8 -> 150000 | I29: =I$8 -> 200000 | J29: =J$8 -> 225000 | K29: =K$8 -> 250000 | M29: =M$8 -> 800000
B30: =C29 -> 1012500000 | C30: and above | G30: =G$8 -> 100000 | H30: =H$8 -> 150000 | I30: =I$8 -> 200000 | J30: =J$8 -> 225000 | K30: =K$8 -> 250000 | L30: =L$8 -> 300000 | M30: =M$8 -> 800000
B35: Breakpoints | E35: Incremental
B36: =B16 -> From | C36: =C16 -> To | E36: Distribution
B38: =B18 -> 0 | C38: =C18 -> 150000000 | E38: =C38-B38 -> 150000000 | G38: Breakpoint 1 - Series F receives liquidation preference
B39: =B19 -> 150000000 | C39: =C19 -> 250000000 | E39: =C39-B39 -> 100000000 | G39: Breakpoint 2 - Series E receives liquidation preference
B40: =B20 -> 250000000 | C40: =C20 -> 272500000 | E40: =C40-B40 -> 22500000 | G40: Breakpoint 3 - Series D receives liquidation preference
B41: =B21 -> 272500000 | C41: =C21 -> 282500000 | E41: =C41-B41 -> 10000000 | G41: Breakpoint 4 - Series C receives liquidation preference
B42: =B22 -> 282500000 | C42: =C22 -> 286250000 | E42: =C42-B42 -> 3750000 | G42: Breakpoint 5 - Series B receives liquidation preference
B43: =B23 -> 286250000 | C43: =C23 -> 287250000 | E43: =C43-B43 -> 1000000 | G43: Breakpoint 6 - Series A receives liquidation preference
B44: =B24 -> 287250000 | C44: =C24 -> 295250000 | E44: =C44-B44 -> 8000000 | G44: Breakpoint 7 - Common recieves distributions until Series A converts
B45: =B25 -> 295250000 | C45: =C25 -> 308750000 | E45: =C45-B45 -> 13500000 | G45: Breakpoint 8 - Series A, Common receive distributions until Series B converts
B46: =B26 -> 308750000 | C46: =C26 -> 335000000 | E46: =C46-B46 -> 26250000 | G46: Breakpoint 9 - Series A, Series B, Common receive disturbtions until Series C converts
B47: =B27 -> 335000000 | C47: =C27 -> 397500000 | E47: =C47-B47 -> 62500000 | G47: Breakpoint 10 - Series A, Series B, Series C, Common receive distributions until Series D converts
B48: =B28 -> 397500000 | C48: =C28 -> 840000000 | E48: =C48-B48 -> 442500000 | G48: Breakpoint 11 - Series A, Series B, Series C, Series D, Common receive distributions until Series E converts
B49: =B29 -> 840000000 | C49: =C29 -> 1012500000 | E49: =C49-B49 -> 172500000 | G49: Breakpoint 12 - Series A, Series B, Series C, Series D, Series E, Common receive distributions until Series E converts
B50: =B30 -> 1012500000 | C50: =C30 -> and above | G50: Breakpoint 13 - All shares receive distributions pro rata
B55: Breakpoints | E55: Total
B56: =B36 -> From | C56: =C36 -> To | E56: Allocation | G56: =G16 -> Series A Preferred | H56: =H16 -> Series B Preferred | I56: =I16 -> Series C Preferred | J56: =J16 -> Series D Preferred | K56: =K16 -> Series E Preferred | L56: =L16 -> Series F Preferred | M56: =M16 -> Common
B58: =B38 -> 0 | C58: =C38 -> 150000000 | E58: =SUM(G58:M58) -> 1 | G58: =G18/SUM($G18:$M18) -> 0 | H58: =H18/SUM($G18:$M18) -> 0 | I58: =I18/SUM($G18:$M18) -> 0 | J58: =J18/SUM($G18:$M18) -> 0 | K58: =K18/SUM($G18:$M18) -> 0 | L58: =L18/SUM($G18:$M18) -> 1 | M58: =M18/SUM($G18:$M18) -> 0
B59: =B39 -> 150000000 | C59: =C39 -> 250000000 | E59: =SUM(G59:M59) -> 1 | G59: =G19/SUM($G19:$M19) -> 0 | H59: =H19/SUM($G19:$M19) -> 0 | I59: =I19/SUM($G19:$M19) -> 0 | J59: =J19/SUM($G19:$M19) -> 0 | K59: =K19/SUM($G19:$M19) -> 1 | L59: =L19/SUM($G19:$M19) -> 0 | M59: =M19/SUM($G19:$M19) -> 0
B60: =B40 -> 250000000 | C60: =C40 -> 272500000 | E60: =SUM(G60:M60) -> 1 | G60: =G20/SUM($G20:$M20) -> 0 | H60: =H20/SUM($G20:$M20) -> 0 | I60: =I20/SUM($G20:$M20) -> 0 | J60: =J20/SUM($G20:$M20) -> 1 | K60: =K20/SUM($G20:$M20) -> 0 | L60: =L20/SUM($G20:$M20) -> 0 | M60: =M20/SUM($G20:$M20) -> 0
B61: =B41 -> 272500000 | C61: =C41 -> 282500000 | E61: =SUM(G61:M61) -> 1 | G61: =G21/SUM($G21:$M21) -> 0 | H61: =H21/SUM($G21:$M21) -> 0 | I61: =I21/SUM($G21:$M21) -> 1 | J61: =J21/SUM($G21:$M21) -> 0 | K61: =K21/SUM($G21:$M21) -> 0 | L61: =L21/SUM($G21:$M21) -> 0 | M61: =M21/SUM($G21:$M21) -> 0
B62: =B42 -> 282500000 | C62: =C42 -> 286250000 | E62: =SUM(G62:M62) -> 1 | G62: =G22/SUM($G22:$M22) -> 0 | H62: =H22/SUM($G22:$M22) -> 1 | I62: =I22/SUM($G22:$M22) -> 0 | J62: =J22/SUM($G22:$M22) -> 0 | K62: =K22/SUM($G22:$M22) -> 0 | L62: =L22/SUM($G22:$M22) -> 0 | M62: =M22/SUM($G22:$M22) -> 0
B63: =B43 -> 286250000 | C63: =C43 -> 287250000 | E63: =SUM(G63:M63) -> 1 | G63: =G23/SUM($G23:$M23) -> 1 | H63: =H23/SUM($G23:$M23) -> 0 | I63: =I23/SUM($G23:$M23) -> 0 | J63: =J23/SUM($G23:$M23) -> 0 | K63: =K23/SUM($G23:$M23) -> 0 | L63: =L23/SUM($G23:$M23) -> 0 | M63: =M23/SUM($G23:$M23) -> 0
B64: =B44 -> 287250000 | C64: =C44 -> 295250000 | E64: =SUM(G64:M64) -> 1 | G64: =G24/SUM($G24:$M24) -> 0 | H64: =H24/SUM($G24:$M24) -> 0 | I64: =I24/SUM($G24:$M24) -> 0 | J64: =J24/SUM($G24:$M24) -> 0 | K64: =K24/SUM($G24:$M24) -> 0 | L64: =L24/SUM($G24:$M24) -> 0 | M64: =M24/SUM($G24:$M24) -> 1
B65: =B45 -> 295250000 | C65: =C45 -> 308750000 | E65: =SUM(G65:M65) -> 1 | G65: =G25/SUM($G25:$M25) -> 0.11111111 | H65: =H25/SUM($G25:$M25) -> 0 | I65: =I25/SUM($G25:$M25) -> 0 | J65: =J25/SUM($G25:$M25) -> 0 | K65: =K25/SUM($G25:$M25) -> 0 | L65: =L25/SUM($G25:$M25) -> 0 | M65: =M25/SUM($G25:$M25) -> 0.88888889
B66: =B46 -> 308750000 | C66: =C46 -> 335000000 | E66: =SUM(G66:M66) -> 1 | G66: =G26/SUM($G26:$M26) -> 0.095238095 | H66: =H26/SUM($G26:$M26) -> 0.14285714 | I66: =I26/SUM($G26:$M26) -> 0 | J66: =J26/SUM($G26:$M26) -> 0 | K66: =K26/SUM($G26:$M26) -> 0 | L66: =L26/SUM($G26:$M26) -> 0 | M66: =M26/SUM($G26:$M26) -> 0.76190476
B67: =B47 -> 335000000 | C67: =C47 -> 397500000 | E67: =SUM(G67:M67) -> 1 | G67: =G27/SUM($G27:$M27) -> 0.08 | H67: =H27/SUM($G27:$M27) -> 0.12 | I67: =I27/SUM($G27:$M27) -> 0.16 | J67: =J27/SUM($G27:$M27) -> 0 | K67: =K27/SUM($G27:$M27) -> 0 | L67: =L27/SUM($G27:$M27) -> 0 | M67: =M27/SUM($G27:$M27) -> 0.64
B68: =B48 -> 397500000 | C68: =C48 -> 840000000 | E68: =SUM(G68:M68) -> 1 | G68: =G28/SUM($G28:$M28) -> 0.06779661 | H68: =H28/SUM($G28:$M28) -> 0.10169492 | I68: =I28/SUM($G28:$M28) -> 0.13559322 | J68: =J28/SUM($G28:$M28) -> 0.15254237 | K68: =K28/SUM($G28:$M28) -> 0 | L68: =L28/SUM($G28:$M28) -> 0 | M68: =M28/SUM($G28:$M28) -> 0.54237288
B69: =B49 -> 840000000 | C69: =C49 -> 1012500000 | E69: =SUM(G69:M69) -> 1 | G69: =G29/SUM($G29:$M29) -> 0.057971014 | H69: =H29/SUM($G29:$M29) -> 0.086956522 | I69: =I29/SUM($G29:$M29) -> 0.11594203 | J69: =J29/SUM($G29:$M29) -> 0.13043478 | K69: =K29/SUM($G29:$M29) -> 0.14492754 | L69: =L29/SUM($G29:$M29) -> 0 | M69: =M29/SUM($G29:$M29) -> 0.46376812
B70: =B50 -> 1012500000 | C70: =C50 -> and above | E70: =SUM(G70:M70) -> 1 | G70: =G30/SUM($G30:$M30) -> 0.049382716 | H70: =H30/SUM($G30:$M30) -> 0.074074074 | I70: =I30/SUM($G30:$M30) -> 0.098765432 | J70: =J30/SUM($G30:$M30) -> 0.11111111 | K70: =K30/SUM($G30:$M30) -> 0.12345679 | L70: =L30/SUM($G30:$M30) -> 0.14814815 | M70: =M30/SUM($G30:$M30) -> 0.39506173
B75: =B55 -> Breakpoints | C75: =C55 -> 0 | E75: Option Value | O75: Call | V75: Incremental
B76: =B56 -> From | C76: =C56 -> To | G76: =G5 -> Series A Preferred | H76: =H5 -> Series B Preferred | I76: =I5 -> Series C Preferred | J76: =J5 -> Series D Preferred | K76: =K5 -> Series E Preferred | L76: =L5 -> Series F Preferred | M76: =M5 -> Common | O76: Option | Q76: N(d1) | R76: N(d2) | S76: d1 | T76: d2 | V76: N(d1)
B78: =B58 -> 0 | C78: =C58 -> 150000000 | E78: =O78-O79 -> 1.3797869e+08 | G78: =$E78*G58 -> 0 | H78: =$E78*H58 -> 0 | I78: =$E78*I58 -> 0 | J78: =$E78*J58 -> 0 | K78: =$E78*K58 -> 0 | L78: =$E78*L58 -> 1.3797869e+08 | M78: =$E78*M58 -> 0 | O78: =C7 -> 6.3922036e+08 | Q78: 1 | V78: =Q78-Q79 -> 0.0032468183
B79: =B59 -> 150000000 | C79: =C59 -> 250000000 | E79: =O79-O80 -> 87338633 | G79: =$E79*G59 -> 0 | H79: =$E79*H59 -> 0 | I79: =$E79*I59 -> 0 | J79: =$E79*J59 -> 0 | K79: =$E79*K59 -> 87338633 | L79: =$E79*L59 -> 0 | M79: =$E79*M59 -> 0 | O79: =$C$7*Q79-B79*EXP(-$C$10*$C$8)*R79 -> 5.0124167e+08 | Q79: =NORMSDIST(S79) -> 0.99675318 | R79: =NORMSDIST(T79) -> 0.98148161 | S79: =(LN($C$7/B79)+($C$10+$C$9*$C$9/2)*$C$8)/($C$9*SQRT($C$8)) -> 2.7217545 | T79: =S79-$C$9*SQRT($C$8) -> 2.0853584 | V79: =Q79-Q80 -> 0.024240954
B80: =B60 -> 250000000 | C80: =C60 -> 272500000 | E80: =O80-O81 -> 18432398 | G80: =$E80*G60 -> 0 | H80: =$E80*H60 -> 0 | I80: =$E80*I60 -> 0 | J80: =$E80*J60 -> 18432398 | K80: =$E80*K60 -> 0 | L80: =$E80*L60 -> 0 | M80: =$E80*M60 -> 0 | O80: =$C$7*Q80-B80*EXP(-$C$10*$C$8)*R80 -> 4.1390303e+08 | Q80: =NORMSDIST(S80) -> 0.97251223 | R80: =NORMSDIST(T80) -> 0.90019673 | S80: =(LN($C$7/B80)+($C$10+$C$9*$C$9/2)*$C$8)/($C$9*SQRT($C$8)) -> 1.9190695 | T80: =S80-$C$9*SQRT($C$8) -> 1.2826734 | V80: =Q80-Q81 -> 0.0097521584
B81: =B61 -> 272500000 | C81: =C61 -> 282500000 | E81: =O81-O82 -> 8015876.1 | G81: =$E81*G61 -> 0 | H81: =$E81*H61 -> 0 | I81: =$E81*I61 -> 8015876.1 | J81: =$E81*J61 -> 0 | K81: =$E81*K61 -> 0 | L81: =$E81*L61 -> 0 | M81: =$E81*M61 -> 0 | O81: =$C$7*Q81-B81*EXP(-$C$10*$C$8)*R81 -> 3.9547064e+08 | Q81: =NORMSDIST(S81) -> 0.96276007 | R81: =NORMSDIST(T81) -> 0.87436253 | S81: =(LN($C$7/B81)+($C$10+$C$9*$C$9/2)*$C$8)/($C$9*SQRT($C$8)) -> 1.7836543 | T81: =S81-$C$9*SQRT($C$8) -> 1.1472582 | V81: =Q81-Q82 -> 0.0048418382
B82: =B62 -> 282500000 | C82: =C62 -> 286250000 | E82: =O82-O83 -> 2976976.8 | G82: =$E82*G62 -> 0 | H82: =$E82*H62 -> 2976976.8 | I82: =$E82*I62 -> 0 | J82: =$E82*J62 -> 0 | K82: =$E82*K62 -> 0 | L82: =$E82*L62 -> 0 | M82: =$E82*M62 -> 0 | O82: =$C$7*Q82-B82*EXP(-$C$10*$C$8)*R82 -> 3.8745476e+08 | Q82: =NORMSDIST(S82) -> 0.95791823 | R82: =NORMSDIST(T82) -> 0.86228145 | S82: =(LN($C$7/B82)+($C$10+$C$9*$C$9/2)*$C$8)/($C$9*SQRT($C$8)) -> 1.727023 | T82: =S82-$C$9*SQRT($C$8) -> 1.0906269 | V82: =Q82-Q83 -> 0.0018942018
B83: =B63 -> 286250000 | C83: =C63 -> 287250000 | E83: =O83-O84 -> 791157.6 | G83: =$E83*G63 -> 791157.6 | H83: =$E83*H63 -> 0 | I83: =$E83*I63 -> 0 | J83: =$E83*J63 -> 0 | K83: =$E83*K63 -> 0 | L83: =$E83*L63 -> 0 | M83: =$E83*M63 -> 0 | O83: =$C$7*Q83-B83*EXP(-$C$10*$C$8)*R83 -> 3.8447778e+08 | Q83: =NORMSDIST(S83) -> 0.95602403 | R83: =NORMSDIST(T83) -> 0.85766907 | S83: =(LN($C$7/B83)+($C$10+$C$9*$C$9/2)*$C$8)/($C$9*SQRT($C$8)) -> 1.7063016 | T83: =S83-$C$9*SQRT($C$8) -> 1.0699055 | V83: =Q83-Q84 -> 0.00051226271
B84: =B64 -> 287250000 | C84: =C64 -> 295250000 | E84: =O84-O85 -> 6287884.4 | G84: =$E84*G64 -> 0 | H84: =$E84*H64 -> 0 | I84: =$E84*I64 -> 0 | J84: =$E84*J64 -> 0 | K84: =$E84*K64 -> 0 | L84: =$E84*L64 -> 0 | M84: =$E84*M64 -> 6287884.4 | O84: =$C$7*Q84-B84*EXP(-$C$10*$C$8)*R84 -> 3.8368663e+08 | Q84: =NORMSDIST(S84) -> 0.95551177 | R84: =NORMSDIST(T84) -> 0.85643204 | S84: =(LN($C$7/B84)+($C$10+$C$9*$C$9/2)*$C$8)/($C$9*SQRT($C$8)) -> 1.7008217 | T84: =S84-$C$9*SQRT($C$8) -> 1.0644256 | V84: =Q84-Q85 -> 0.004205073
B85: =B65 -> 295250000 | C85: =C65 -> 308750000 | E85: =O85-O86 -> 10441376 | G85: =$E85*G65 -> 1160152.9 | H85: =$E85*H65 -> 0 | I85: =$E85*I65 -> 0 | J85: =$E85*J65 -> 0 | K85: =$E85*K65 -> 0 | L85: =$E85*L65 -> 0 | M85: =$E85*M65 -> 9281223.5 | O85: =$C$7*Q85-B85*EXP(-$C$10*$C$8)*R85 -> 3.7739874e+08 | Q85: =NORMSDIST(S85) -> 0.95130669 | R85: =NORMSDIST(T85) -> 0.8464347 | S85: =(LN($C$7/B85)+($C$10+$C$9*$C$9/2)*$C$8)/($C$9*SQRT($C$8)) -> 1.6576575 | T85: =S85-$C$9*SQRT($C$8) -> 1.0212614 | V85: =Q85-Q86 -> 0.0075173458
B86: =B66 -> 308750000 | C86: =C66 -> 335000000 | E86: =O86-O87 -> 19677066 | G86: =$E86*G66 -> 1874006.3 | H86: =$E86*H66 -> 2811009.5 | I86: =$E86*I66 -> 0 | J86: =$E86*J66 -> 0 | K86: =$E86*K66 -> 0 | L86: =$E86*L66 -> 0 | M86: =$E86*M66 -> 14992050 | O86: =$C$7*Q86-B86*EXP(-$C$10*$C$8)*R86 -> 3.6695736e+08 | Q86: =NORMSDIST(S86) -> 0.94378935 | R86: =NORMSDIST(T86) -> 0.82919967 | S86: =(LN($C$7/B86)+($C$10+$C$9*$C$9/2)*$C$8)/($C$9*SQRT($C$8)) -> 1.5874034 | T86: =S86-$C$9*SQRT($C$8) -> 0.95100732 | V86: =Q86-Q87 -> 0.016046649
B87: =B67 -> 335000000 | C87: =C67 -> 397500000 | E87: =O87-O88 -> 43417584 | G87: =$E87*G67 -> 3473406.7 | H87: =$E87*H67 -> 5210110.1 | I87: =$E87*I67 -> 6946813.4 | J87: =$E87*J67 -> 0 | K87: =$E87*K67 -> 0 | L87: =$E87*L67 -> 0 | M87: =$E87*M67 -> 27787254 | O87: =$C$7*Q87-B87*EXP(-$C$10*$C$8)*R87 -> 3.472803e+08 | Q87: =NORMSDIST(S87) -> 0.9277427 | R87: =NORMSDIST(T87) -> 0.79468555 | S87: =(LN($C$7/B87)+($C$10+$C$9*$C$9/2)*$C$8)/($C$9*SQRT($C$8)) -> 1.4591835 | T87: =S87-$C$9*SQRT($C$8) -> 0.82278742 | V87: =Q87-Q88 -> 0.04469089
B88: =B68 -> 397500000 | C88: =C68 -> 840000000 | E88: =O88-O89 -> 1.8759547e+08 | G88: =$E88*G68 -> 12718337 | H88: =$E88*H68 -> 19077506 | I88: =$E88*I68 -> 25436674 | J88: =$E88*J68 -> 28616259 | K88: =$E88*K68 -> 0 | L88: =$E88*L68 -> 0 | M88: =$E88*M68 -> 1.017467e+08 | O88: =$C$7*Q88-B88*EXP(-$C$10*$C$8)*R88 -> 3.0386271e+08 | Q88: =NORMSDIST(S88) -> 0.88305181 | R88: =NORMSDIST(T88) -> 0.71020567 | S88: =(LN($C$7/B88)+($C$10+$C$9*$C$9/2)*$C$8)/($C$9*SQRT($C$8)) -> 1.1903818 | T88: =S88-$C$9*SQRT($C$8) -> 0.55398565 | V88: =Q88-Q89 -> 0.37719238
B89: =B69 -> 840000000 | C89: =C69 -> 1012500000 | E89: =O89-O90 -> 35123399 | G89: =$E89*G69 -> 2036139.1 | H89: =$E89*H69 -> 3054208.6 | I89: =$E89*I69 -> 4072278.1 | J89: =$E89*J69 -> 4581312.9 | K89: =$E89*K69 -> 5090347.7 | L89: =$E89*L69 -> 0 | M89: =$E89*M69 -> 16289113 | O89: =$C$7*Q89-B89*EXP(-$C$10*$C$8)*R89 -> 1.1626724e+08 | Q89: =NORMSDIST(S89) -> 0.50585943 | R89: =NORMSDIST(T89) -> 0.26706689 | S89: =(LN($C$7/B89)+($C$10+$C$9*$C$9/2)*$C$8)/($C$9*SQRT($C$8)) -> 0.014687943 | T89: =S89-$C$9*SQRT($C$8) -> -0.62170816 | V89: =Q89-Q90 -> 0.11566107
B90: =B70 -> 1012500000 | C90: =C70 -> and above | E90: =O90-O91 -> 81143843 | G90: =$E90*G70 -> 4007103.4 | H90: =$E90*H70 -> 6010655 | I90: =$E90*I70 -> 8014206.7 | J90: =$E90*J70 -> 9015982.6 | K90: =$E90*K70 -> 10017758 | L90: =$E90*L70 -> 12021310 | M90: =$E90*M70 -> 32056827 | O90: =$C$7*Q90-B90*EXP(-$C$10*$C$8)*R90 -> 81143843 | Q90: =NORMSDIST(S90) -> 0.39019836 | R90: =NORMSDIST(T90) -> 0.1800438 | S90: =(LN($C$7/B90)+($C$10+$C$9*$C$9/2)*$C$8)/($C$9*SQRT($C$8)) -> -0.27880208 | T90: =S90-$C$9*SQRT($C$8) -> -0.91519818 | V90: =Q90-Q91 -> 0.39019836
E93: Fair Value (per class) | G93: =SUM(G78:G90) -> 26060303 | H93: =SUM(H78:H90) -> 39140466 | I93: =SUM(I78:I90) -> 52485849 | J93: =SUM(J78:J90) -> 60645952 | K93: =SUM(K78:K90) -> 1.0244674e+08 | L93: =SUM(L78:L90) -> 1.5e+08 | M93: =SUM(M78:M90) -> 2.0844105e+08
E95: Fair Value (per share) | G95: =G93/G8 -> 260.60303 | H95: =H93/H8 -> 260.93644 | I95: =I93/I8 -> 262.42924 | J95: =J93/J8 -> 269.53756 | K95: =K93/K8 -> 409.78696 | L95: =L93/L8 -> 500 | M95: =M93/M8 -> 260.55131
E97: Series Specific Volatility | G97: =$C$9*SUMPRODUCT(G58:G70,$V$78:$V$90)*($C$7/G93) -> 0.64016598 | H97: =$C$9*SUMPRODUCT(H58:H70,$V$78:$V$90)*($C$7/H93) -> 0.63841407 | I97: =$C$9*SUMPRODUCT(I58:I70,$V$78:$V$90)*($C$7/I93) -> 0.63072546 | J97: =$C$9*SUMPRODUCT(J58:J70,$V$78:$V$90)*($C$7/J93) -> 0.59635609 | K97: =$C$9*SUMPRODUCT(K58:K70,$V$78:$V$90)*($C$7/K93) -> 0.25038786 | L97: =$C$9*SUMPRODUCT(L58:L70,$V$78:$V$90)*($C$7/L93) -> 0.11708085 | M97: =$C$9*SUMPRODUCT(M58:M70,$V$78:$V$90)*($C$7/M93) -> 0.64044068
K102: Target | L102: ='1.a Capital Structure'!E7*'1.a Capital Structure'!C7 -> 150000000
K103: Diff | L103: =L93-L102 -> 2.0265579e-06

Sheet 2.a Capital Structure
A1: class_name | B1: type | C1: sharecount | D1: seniority | E1: liquidation_preference_per_share | F1: convertible | G1: conversion_ratio | H1: participating | I1: participation_cap_multiple
A2: Series A Preferred | B2: Preferred | C2: 100000 | D2: 6 | E2: 10 | F2: TRUE | G2: 1 | H2: TRUE
A3: Series B Preferred | B3: Preferred | C3: 150000 | D3: 5 | E3: 25 | F3: TRUE | G3: 1 | H3: TRUE
A4: Series C Preferred | B4: Preferred | C4: 200000 | D4: 4 | E4: 50 | F4: TRUE | G4: 1 | H4: TRUE
A5: Series D Preferred | B5: Preferred | C5: 225000 | D5: 3 | E5: 100 | F5: TRUE | G5: 1 | H5: TRUE
A6: Series E Preferred | B6: Preferred | C6: 250000 | D6: 2 | E6: 400 | F6: TRUE | G6: 1 | H6: TRUE
A7: Series F Preferred | B7: Preferred | C7: 300000 | D7: 1 | E7: 500 | F7: TRUE | G7: 1 | H7: TRUE
A8: Common | B8: Common | C8: 800000

Sheet 2.b OPM
B5: Inputs & Assumptions | G5: Series A Preferred | H5: Series B Preferred | I5: Series C Preferred | J5: Series D Preferred | K5: Series E Preferred | L5: Series F Preferred | M5: Common
B7: Equity Value | C7: 750000000 | G7: ='2.a Capital Structure'!D2 -> 6 | H7: ='2.a Capital Structure'!D3 -> 5 | I7: ='2.a Capital Structure'!D4 -> 4 | J7: ='2.a Capital Structure'!D5 -> 3 | K7: ='2.a Capital Structure'!D6 -> 2 | L7: ='2.a Capital Structure'!D7 -> 1 | N7: Priority
B8: T | C8: 2 | G8: ='2.a Capital Structure'!C2 -> 100000 | H8: ='2.a Capital Structure'!C3 -> 150000 | I8: ='2.a Capital Structure'!C4 -> 200000 | J8: ='2.a Capital Structure'!C5 -> 225000 | K8: ='2.a Capital Structure'!C6 -> 250000 | L8: ='2.a Capital Structure'!C7 -> 300000 | M8: ='2.a Capital Structure'!C8 -> 800000 | N8: Sharecount
B9: Volatility | C9: 0.45 | G9: ='2.a Capital Structure'!E2 -> 10 | H9: ='2.a Capital Structure'!E3 -> 25 | I9: ='2.a Capital Structure'!E4 -> 50 | J9: ='2.a Capital Structure'!E5 -> 100 | K9: ='2.a Capital Structure'!E6 -> 400 | L9: ='2.a Capital Structure'!E7 -> 500 | N9: Liquidation Preference (per share)
B10: Risk-free Rate | C10: 0.04 | G10: =G8*G9 -> 1000000 | H10: =H8*H9 -> 3750000 | I10: =I8*I9 -> 10000000 | J10: =J8*J9 -> 22500000 | K10: =K8*K9 -> 100000000 | L10: =L8*L9 -> 150000000 | N10: Liquidation Preference (total)
B15: Breakpoints
B16: From | C16: To | G16: =G5 -> Series A Preferred | H16: =H5 -> Series B Preferred | I16: =I5 -> Series C Preferred | J16: =J5 -> Series D Preferred | K16: =K5 -> Series E Preferred | L16: =L5 -> Series F Preferred | M16: =M5 -> Common
B18: 0 | C18: =B18+SUM(G18:L18) -> 150000000 | L18: =L10 -> 150000000
B19: =C18 -> 150000000 | C19: =B19+SUM(G19:L19) -> 250000000 | K19: =K10 -> 100000000
B20: =C19 -> 250000000 | C20: =B20+SUM(G20:L20) -> 272500000 | J20: =J10 -> 22500000
B21: =C20 -> 272500000 | C21: =B21+SUM(G21:L21) -> 282500000 | I21: =I10 -> 10000000
B22: =C21 -> 282500000 | C22: =B22+SUM(G22:L22) -> 286250000 | H22: =H10 -> 3750000
B23: =C22 -> 286250000 | C23: =B23+SUM(G23:L23) -> 287250000 | G23: =G10 -> 1000000
B24: =C23 -> 287250000 | C24: and above | G24: =G$8 -> 100000 | H24: =H$8 -> 150000 | I24: =I$8 -> 200000 | J24: =J$8 -> 225000 | K24: =K$8 -> 250000 | L24: =L$8 -> 300000 | M24: =M$8 -> 800000
B29: Breakpoints | E29: Incremental
B30: =B16 -> From | C30: =C16 -> To | E30: Distribution
B32: =B18 -> 0 | C32: =C18 -> 150000000 | E32: =C32-B32 -> 150000000 | G32: Breakpoint 1 - Series F receives liquidation preference
B33: =B19 -> 150000000 | C33: =C19 -> 250000000 | E33: =C33-B33 -> 100000000 | G33: Breakpoint 2 - Series E receives liquidation preference
B34: =B20 -> 250000000 | C34: =C20 -> 272500000 | E34: =C34-B34 -> 22500000 | G34: Breakpoint 3 - Series D receives liquidation preference
B35: =B21 -> 272500000 | C35: =C21 -> 282500000 | E35: =C35-B35 -> 10000000 | G35: Breakpoint 4 - Series C receives liquidation preference
B36: =B22 -> 282500000 | C36: =C22 -> 286250000 | E36: =C36-B36 -> 3750000 | G36: Breakpoint 5 - Series B receives liquidation preference
B37: =B23 -> 286250000 | C37: =C23 -> 287250000 | E37: =C37-B37 -> 1000000 | G37: Breakpoint 6 - Series A receives liquidation preference
B38: =B24 -> 287250000 | C38: =C24 -> and above | G38: Breakpoint 7 - All shares receive distributions pro rata
B43: Breakpoints | E43: Total
B44: =B30 -> From | C44: =C30 -> To | E44: Allocation | G44: =G16 -> Series A Preferred | H44: =H16 -> Series B Preferred | I44: =I16 -> Series C Preferred | J44: =J16 -> Series D Preferred | K44: =K16 -> Series E Preferred | L44: =L16 -> Series F Preferred | M44: =M16 -> Common
B46: =B32 -> 0 | C46: =C32 -> 150000000 | E46: =SUM(G46:M46) -> 1 | G46: =G18/SUM($G18:$M18) -> 0 | H46: =H18/SUM($G18:$M18) -> 0 | I46: =I18/SUM($G18:$M18) -> 0 | J46: =J18/SUM($G18:$M18) -> 0 | K46: =K18/SUM($G18:$M18) -> 0 | L46: =L18/SUM($G18:$M18) -> 1 | M46: =M18/SUM($G18:$M18) -> 0
B47: =B33 -> 150000000 | C47: =C33 -> 250000000 | E47: =SUM(G47:M47) -> 1 | G47: =G19/SUM($G19:$M19) -> 0 | H47: =H19/SUM($G19:$M19) -> 0 | I47: =I19/SUM($G19:$M19) -> 0 | J47: =J19/SUM($G19:$M19) -> 0 | K47: =K19/SUM($G19:$M19) -> 1 | L47: =L19/SUM($G19:$M19) -> 0 | M47: =M19/SUM($G19:$M19) -> 0
B48: =B34 -> 250000000 | C48: =C34 -> 272500000 | E48: =SUM(G48:M48) -> 1 | G48: =G20/SUM($G20:$M20) -> 0 | H48: =H20/SUM($G20:$M20) -> 0 | I48: =I20/SUM($G20:$M20) -> 0 | J48: =J20/SUM($G20:$M20) -> 1 | K48: =K20/SUM($G20:$M20) -> 0 | L48: =L20/SUM($G20:$M20) -> 0 | M48: =M20/SUM($G20:$M20) -> 0
B49: =B35 -> 272500000 | C49: =C35 -> 282500000 | E49: =SUM(G49:M49) -> 1 | G49: =G21/SUM($G21:$M21) -> 0 | H49: =H21/SUM($G21:$M21) -> 0 | I49: =I21/SUM($G21:$M21) -> 1 | J49: =J21/SUM($G21:$M21) -> 0 | K49: =K21/SUM($G21:$M21) -> 0 | L49: =L21/SUM($G21:$M21) -> 0 | M49: =M21/SUM($G21:$M21) -> 0
B50: =B36 -> 282500000 | C50: =C36 -> 286250000 | E50: =SUM(G50:M50) -> 1 | G50: =G22/SUM($G22:$M22) -> 0 | H50: =H22/SUM($G22:$M22) -> 1 | I50: =I22/SUM($G22:$M22) -> 0 | J50: =J22/SUM($G22:$M22) -> 0 | K50: =K22/SUM($G22:$M22) -> 0 | L50: =L22/SUM($G22:$M22) -> 0 | M50: =M22/SUM($G22:$M22) -> 0
B51: =B37 -> 286250000 | C51: =C37 -> 287250000 | E51: =SUM(G51:M51) -> 1 | G51: =G23/SUM($G23:$M23) -> 1 | H51: =H23/SUM($G23:$M23) -> 0 | I51: =I23/SUM($G23:$M23) -> 0 | J51: =J23/SUM($G23:$M23) -> 0 | K51: =K23/SUM($G23:$M23) -> 0 | L51: =L23/SUM($G23:$M23) -> 0 | M51: =M23/SUM($G23:$M23) -> 0
B52: =B38 -> 287250000 | C52: =C38 -> and above | E52: =SUM(G52:M52) -> 1 | G52: =G24/SUM($G24:$M24) -> 0.049382716 | H52: =H24/SUM($G24:$M24) -> 0.074074074 | I52: =I24/SUM($G24:$M24) -> 0.098765432 | J52: =J24/SUM($G24:$M24) -> 0.11111111 | K52: =K24/SUM($G24:$M24) -> 0.12345679 | L52: =L24/SUM($G24:$M24) -> 0.14814815 | M52: =M24/SUM($G24:$M24) -> 0.39506173
B57: =B43 -> Breakpoints | C57: =C43 -> 0 | E57: Option Value | O57: Call | V57: Incremental
B58: =B44 -> From | C58: =C44 -> To | G58: =G5 -> Series A Preferred | H58: =H5 -> Series B Preferred | I58: =I5 -> Series C Preferred | J58: =J5 -> Series D Preferred | K58: =K5 -> Series E Preferred | L58: =L5 -> Series F Preferred | M58: =M5 -> Common | O58: Option | Q58: N(d1) | R58: N(d2) | S58: d1 | T58: d2 | V58: N(d1)
B60: =B46 -> 0 | C60: =C46 -> 150000000 | E60: =O60-O61 -> 1.3822607e+08 | G60: =$E60*G46 -> 0 | H60: =$E60*H46 -> 0 | I60: =$E60*I46 -> 0 | J60: =$E60*J46 -> 0 | K60: =$E60*K46 -> 0 | L60: =$E60*L46 -> 1.3822607e+08 | M60: =$E60*M46 -> 0 | O60: =C7 -> 750000000 | Q60: 1 | V60: =Q60-Q61 -> 0.0014750334
B61: =B47 -> 150000000 | C61: =C47 -> 250000000 | E61: =O61-O62 -> 89367221 | G61: =$E61*G47 -> 0 | H61: =$E61*H47 -> 0 | I61: =$E61*I47 -> 0 | J61: =$E61*J47 -> 0 | K61: =$E61*K47 -> 89367221 | L61: =$E61*L47 -> 0 | M61: =$E61*M47 -> 0 | O61: =$C$7*Q61-B61*EXP(-$C$10*$C$8)*R61 -> 6.1177393e+08 | Q61: =NORMSDIST(S61) -> 0.99852497 | R61: =NORMSDIST(T61) -> 0.99026734 | S61: =(LN($C$7/B61)+($C$10+$C$9*$C$9/2)*$C$8)/($C$9*SQRT($C$8)) -> 2.9728936 | T61: =S61-$C$9*SQRT($C$8) -> 2.3364975 | V61: =Q61-Q62 -> 0.01352049
B62: =B48 -> 250000000 | C62: =C48 -> 272500000 | E62: =O62-O63 -> 19283083 | G62: =$E62*G48 -> 0 | H62: =$E62*H48 -> 0 | I62: =$E62*I48 -> 0 | J62: =$E62*J48 -> 19283083 | K62: =$E62*K48 -> 0 | L62: =$E62*L48 -> 0 | M62: =$E62*M48 -> 0 | O62: =$C$7*Q62-B62*EXP(-$C$10*$C$8)*R62 -> 5.2240671e+08 | Q62: =NORMSDIST(S62) -> 0.98500448 | R62: =NORMSDIST(T62) -> 0.9374621 | S62: =(LN($C$7/B62)+($C$10+$C$9*$C$9/2)*$C$8)/($C$9*SQRT($C$8)) -> 2.1702086 | T62: =S62-$C$9*SQRT($C$8) -> 1.5338125 | V62: =Q62-Q63 -> 0.0059403087
B63: =B49 -> 272500000 | C63: =C49 -> 282500000 | E63: =O63-O64 -> 8442953 | G63: =$E63*G49 -> 0 | H63: =$E63*H49 -> 0 | I63: =$E63*I49 -> 8442953 | J63: =$E63*J49 -> 0 | K63: =$E63*K49 -> 0 | L63: =$E63*L49 -> 0 | M63: =$E63*M49 -> 0 | O63: =$C$7*Q63-B63*EXP(-$C$10*$C$8)*R63 -> 5.0312363e+08 | Q63: =NORMSDIST(S63) -> 0.97906417 | R63: =NORMSDIST(T63) -> 0.9190031 | S63: =(LN($C$7/B63)+($C$10+$C$9*$C$9/2)*$C$8)/($C$9*SQRT($C$8)) -> 2.0347934 | T63: =S63-$C$9*SQRT($C$8) -> 1.3983973 | V63: =Q63-Q64 -> 0.0030193785
B64: =B50 -> 282500000 | C64: =C50 -> 286250000 | E64: =O64-O65 -> 3144819.1 | G64: =$E64*G50 -> 0 | H64: =$E64*H50 -> 3144819.1 | I64: =$E64*I50 -> 0 | J64: =$E64*J50 -> 0 | K64: =$E64*K50 -> 0 | L64: =$E64*L50 -> 0 | M64: =$E64*M50 -> 0 | O64: =$C$7*Q64-B64*EXP(-$C$10*$C$8)*R64 -> 4.9468067e+08 | Q64: =NORMSDIST(S64) -> 0.97604479 | R64: =NORMSDIST(T64) -> 0.91016406 | S64: =(LN($C$7/B64)+($C$10+$C$9*$C$9/2)*$C$8)/($C$9*SQRT($C$8)) -> 1.9781621 | T64: =S64-$C$9*SQRT($C$8) -> 1.341766 | V64: =Q64-Q65 -> 0.001192626
B65: =B51 -> 286250000 | C65: =C51 -> 287250000 | E65: =O65-O66 -> 836619.07 | G65: =$E65*G51 -> 836619.07 | H65: =$E65*H51 -> 0 | I65: =$E65*I51 -> 0 | J65: =$E65*J51 -> 0 | K65: =$E65*K51 -> 0 | L65: =$E65*L51 -> 0 | M65: =$E65*M51 -> 0 | O65: =$C$7*Q65-B65*EXP(-$C$10*$C$8)*R65 -> 4.9153585e+08 | Q65: =NORMSDIST(S65) -> 0.97485216 | R65: =NORMSDIST(T65) -> 0.90675676 | S65: =(LN($C$7/B65)+($C$10+$C$9*$C$9/2)*$C$8)/($C$9*SQRT($C$8)) -> 1.9574407 | T65: =S65-$C$9*SQRT($C$8) -> 1.3210446 | V65: =Q65-Q66 -> 0.00032358839
B66: =B52 -> 287250000 | C66: =C52 -> and above | E66: =O66-O67 -> 4.9069923e+08 | G66: =$E66*G52 -> 24232061 | H66: =$E66*H52 -> 36348091 | I66: =$E66*I52 -> 48464122 | J66: =$E66*J52 -> 54522137 | K66: =$E66*K52 -> 60580152 | L66: =$E66*L52 -> 72696183 | M66: =$E66*M52 -> 1.9385649e+08 | O66: =$C$7*Q66-B66*EXP(-$C$10*$C$8)*R66 -> 4.9069923e+08 | Q66: =NORMSDIST(S66) -> 0.97452857 | R66: =NORMSDIST(T66) -> 0.90583992 | S66: =(LN($C$7/B66)+($C$10+$C$9*$C$9/2)*$C$8)/($C$9*SQRT($C$8)) -> 1.9519609 | T66: =S66-$C$9*SQRT($C$8) -> 1.3155648 | V66: =Q66-Q67 -> 0.97452857
E69: Fair Value (per class) | G69: =SUM(G60:G66) -> 25068680 | H69: =SUM(H60:H66) -> 39492911 | I69: =SUM(I60:I66) -> 56907075 | J69: =SUM(J60:J66) -> 73805220 | K69: =SUM(K60:K66) -> 1.4994737e+08 | L69: =SUM(L60:L66) -> 2.1092225e+08 | M69: =SUM(M60:M66) -> 1.9385649e+08
E71: Fair Value (per share) | G71: =G69/G8 -> 250.6868 | H71: =H69/H8 -> 263.28607 | I71: =I69/I8 -> 284.53537 | J71: =J69/J8 -> 328.0232 | K71: =K69/K8 -> 599.78949 | L71: =L69/L8 -> 703.07418 | M71: =M69/M8 -> 242.32061
E73: Series Specific Volatility | G73: =$C$9*SUMPRODUCT(G46:G52,$V$60:$V$66)*($C$7/G69) -> 0.65226226 | H73: =$C$9*SUMPRODUCT(H46:H52,$V$60:$V$66)*($C$7/H69) -> 0.62709295 | I73: =$C$9*SUMPRODUCT(I46:I52,$V$60:$V$66)*($C$7/I69) -> 0.58873745 | J73: =$C$9*SUMPRODUCT(J46:J52,$V$60:$V$66)*($C$7/J69) -> 0.52231639 | K73: =$C$9*SUMPRODUCT(K46:K52,$V$60:$V$66)*($C$7/K69) -> 0.30122917 | L73: =$C$9*SUMPRODUCT(L46:L52,$V$60:$V$66)*($C$7/L69) -> 0.23337629 | M73: =$C$9*SUMPRODUCT(M46:M52,$V$60:$V$66)*($C$7/M69) -> 0.67027493

Sheet 2.c OPM (backsolve)
B5: Inputs & Assumptions | G5: Series A Preferred | H5: Series B Preferred | I5: Series C Preferred | J5: Series D Preferred | K5: Series E Preferred | L5: Series F Preferred | M5: Common
B7: Equity Value | C7: 3.3195167e+08 | G7: ='2.a Capital Structure'!D2 -> 6 | H7: ='2.a Capital Structure'!D3 -> 5 | I7: ='2.a Capital Structure'!D4 -> 4 | J7: ='2.a Capital Structure'!D5 -> 3 | K7: ='2.a Capital Structure'!D6 -> 2 | L7: ='2.a Capital Structure'!D7 -> 1 | N7: Priority
B8: T | C8: 2 | G8: ='2.a Capital Structure'!C2 -> 100000 | H8: ='2.a Capital Structure'!C3 -> 150000 | I8: ='2.a Capital Structure'!C4 -> 200000 | J8: ='2.a Capital Structure'!C5 -> 225000 | K8: ='2.a Capital Structure'!C6 -> 250000 | L8: ='2.a Capital Structure'!C7 -> 300000 | M8: ='2.a Capital Structure'!C8 -> 800000 | N8: Sharecount
B9: Volatility | C9: 0.45 | G9: ='2.a Capital Structure'!E2 -> 10 | H9: ='2.a Capital Structure'!E3 -> 25 | I9: ='2.a Capital Structure'!E4 -> 50 | J9: ='2.a Capital Structure'!E5 -> 100 | K9: ='2.a Capital Structure'!E6 -> 400 | L9: ='2.a Capital Structure'!E7 -> 500 | N9: Liquidation Preference (per share)
B10: Risk-free Rate | C10: 0.04 | G10: =G8*G9 -> 1000000 | H10: =H8*H9 -> 3750000 | I10: =I8*I9 -> 10000000 | J10: =J8*J9 -> 22500000 | K10: =K8*K9 -> 100000000 | L10: =L8*L9 -> 150000000 | N10: Liquidation Preference (total)
B15: Breakpoints
B16: From | C16: To | G16: =G5 -> Series A Preferred | H16: =H5 -> Series B Preferred | I16: =I5 -> Series C Preferred | J16: =J5 -> Series D Preferred | K16: =K5 -> Series E Preferred | L16: =L5 -> Series F Preferred | M16: =M5 -> Common
B18: 0 | C18: =B18+SUM(G18:L18) -> 150000000 | L18: =L10 -> 150000000
B19: =C18 -> 150000000 | C19: =B19+SUM(G19:L19) -> 250000000 | K19: =K10 -> 100000000
B20: =C19 -> 250000000 | C20: =B20+SUM(G20:L20) -> 272500000 | J20: =J10 -> 22500000
B21: =C20 -> 272500000 | C21: =B21+SUM(G21:L21) -> 282500000 | I21: =I10 -> 10000000
B22: =C21 -> 282500000 | C22: =B22+SUM(G22:L22) -> 286250000 | H22: =H10 -> 3750000
B23: =C22 -> 286250000 | C23: =B23+SUM(G23:L23) -> 287250000 | G23: =G10 -> 1000000
B24: =C23 -> 287250000 | C24: and above | G24: =G$8 -> 100000 | H24: =H$8 -> 150000 | I24: =I$8 -> 200000 | J24: =J$8 -> 225000 | K24: =K$8 -> 250000 | L24: =L$8 -> 300000 | M24: =M$8 -> 800000
B29: Breakpoints | E29: Incremental
B30: =B16 -> From | C30: =C16 -> To | E30: Distribution
B32: =B18 -> 0 | C32: =C18 -> 150000000 | E32: =C32-B32 -> 150000000 | G32: Breakpoint 1 - Series F receives liquidation preference
B33: =B19 -> 150000000 | C33: =C19 -> 250000000 | E33: =C33-B33 -> 100000000 | G33: Breakpoint 2 - Series E receives liquidation preference
B34: =B20 -> 250000000 | C34: =C20 -> 272500000 | E34: =C34-B34 -> 22500000 | G34: Breakpoint 3 - Series D receives liquidation preference
B35: =B21 -> 272500000 | C35: =C21 -> 282500000 | E35: =C35-B35 -> 10000000 | G35: Breakpoint 4 - Series C receives liquidation preference
B36: =B22 -> 282500000 | C36: =C22 -> 286250000 | E36: =C36-B36 -> 3750000 | G36: Breakpoint 5 - Series B receives liquidation preference
B37: =B23 -> 286250000 | C37: =C23 -> 287250000 | E37: =C37-B37 -> 1000000 | G37: Breakpoint 6 - Series A receives liquidation preference
B38: =B24 -> 287250000 | C38: =C24 -> and above | G38: Breakpoint 7 - All shares receive distributions pro rata
B43: Breakpoints | E43: Total
B44: =B30 -> From | C44: =C30 -> To | E44: Allocation | G44: =G16 -> Series A Preferred | H44: =H16 -> Series B Preferred | I44: =I16 -> Series C Preferred | J44: =J16 -> Series D Preferred | K44: =K16 -> Series E Preferred | L44: =L16 -> Series F Preferred | M44: =M16 -> Common
B46: =B32 -> 0 | C46: =C32 -> 150000000 | E46: =SUM(G46:M46) -> 1 | G46: =G18/SUM($G18:$M18) -> 0 | H46: =H18/SUM($G18:$M18) -> 0 | I46: =I18/SUM($G18:$M18) -> 0 | J46: =J18/SUM($G18:$M18) -> 0 | K46: =K18/SUM($G18:$M18) -> 0 | L46: =L18/SUM($G18:$M18) -> 1 | M46: =M18/SUM($G18:$M18) -> 0
B47: =B33 -> 150000000 | C47: =C33 -> 250000000 | E47: =SUM(G47:M47) -> 1 | G47: =G19/SUM($G19:$M19) -> 0 | H47: =H19/SUM($G19:$M19) -> 0 | I47: =I19/SUM($G19:$M19) -> 0 | J47: =J19/SUM($G19:$M19) -> 0 | K47: =K19/SUM($G19:$M19) -> 1 | L47: =L19/SUM($G19:$M19) -> 0 | M47: =M19/SUM($G19:$M19) -> 0
B48: =B34 -> 250000000 | C48: =C34 -> 272500000 | E48: =SUM(G48:M48) -> 1 | G48: =G20/SUM($G20:$M20) -> 0 | H48: =H20/SUM($G20:$M20) -> 0 | I48: =I20/SUM($G20:$M20) -> 0 | J48: =J20/SUM($G20:$M20) -> 1 | K48: =K20/SUM($G20:$M20) -> 0 | L48: =L20/SUM($G20:$M20) -> 0 | M48: =M20/SUM($G20:$M20) -> 0
B49: =B35 -> 272500000 | C49: =C35 -> 282500000 | E49: =SUM(G49:M49) -> 1 | G49: =G21/SUM($G21:$M21) -> 0 | H49: =H21/SUM($G21:$M21) -> 0 | I49: =I21/SUM($G21:$M21) -> 1 | J49: =J21/SUM($G21:$M21) -> 0 | K49: =K21/SUM($G21:$M21) -> 0 | L49: =L21/SUM($G21:$M21) -> 0 | M49: =M21/SUM($G21:$M21) -> 0
B50: =B36 -> 282500000 | C50: =C36 -> 286250000 | E50: =SUM(G50:M50) -> 1 | G50: =G22/SUM($G22:$M22) -> 0 | H50: =H22/SUM($G22:$M22) -> 1 | I50: =I22/SUM($G22:$M22) -> 0 | J50: =J22/SUM($G22:$M22) -> 0 | K50: =K22/SUM($G22:$M22) -> 0 | L50: =L22/SUM($G22:$M22) -> 0 | M50: =M22/SUM($G22:$M22) -> 0
B51: =B37 -> 286250000 | C51: =C37 -> 287250000 | E51: =SUM(G51:M51) -> 1 | G51: =G23/SUM($G23:$M23) -> 1 | H51: =H23/SUM($G23:$M23) -> 0 | I51: =I23/SUM($G23:$M23) -> 0 | J51: =J23/SUM($G23:$M23) -> 0 | K51: =K23/SUM($G23:$M23) -> 0 | L51: =L23/SUM($G23:$M23) -> 0 | M51: =M23/SUM($G23:$M23) -> 0
B52: =B38 -> 287250000 | C52: =C38 -> and above | E52: =SUM(G52:M52) -> 1 | G52: =G24/SUM($G24:$M24) -> 0.049382716 | H52: =H24/SUM($G24:$M24) -> 0.074074074 | I52: =I24/SUM($G24:$M24) -> 0.098765432 | J52: =J24/SUM($G24:$M24) -> 0.11111111 | K52: =K24/SUM($G24:$M24) -> 0.12345679 | L52: =L24/SUM($G24:$M24) -> 0.14814815 | M52: =M24/SUM($G24:$M24) -> 0.39506173
B57: =B43 -> Breakpoints | C57: =C43 -> 0 | E57: Option Value | O57: Call | V57: Incremental
B58: =B44 -> From | C58: =C44 -> To | G58: =G5 -> Series A Preferred | H58: =H5 -> Series B Preferred | I58: =I5 -> Series C Preferred | J58: =J5 -> Series D Preferred | K58: =K5 -> Series E Preferred | L58: =L5 -> Series F Preferred | M58: =M5 -> Common | O58: Option | Q58: N(d1) | R58: N(d2) | S58: d1 | T58: d2 | V58: N(d1)
B60: =B46 -> 0 | C60: =C46 -> 150000000 | E60: =O60-O61 -> 1.3335515e+08 | G60: =$E60*G46 -> 0 | H60: =$E60*H46 -> 0 | I60: =$E60*I46 -> 0 | J60: =$E60*J46 -> 0 | K60: =$E60*K46 -> 0 | L60: =$E60*L46 -> 1.3335515e+08 | M60: =$E60*M46 -> 0 | O60: =C7 -> 3.3195167e+08 | Q60: 1 | V60: =Q60-Q61 -> 0.045312218
B61: =B47 -> 150000000 | C61: =C47 -> 250000000 | E61: =O61-O62 -> 67121503 | G61: =$E61*G47 -> 0 | H61: =$E61*H47 -> 0 | I61: =$E61*I47 -> 0 | J61: =$E61*J47 -> 0 | K61: =$E61*K47 -> 67121503 | L61: =$E61*L47 -> 0 | M61: =$E61*M47 -> 0 | O61: =$C$7*Q61-B61*EXP(-$C$10*$C$8)*R61 -> 1.9859652e+08 | Q61: =NORMSDIST(S61) -> 0.95468778 | R61: =NORMSDIST(T61) -> 0.85445121 | S61: =(LN($C$7/B61)+($C$10+$C$9*$C$9/2)*$C$8)/($C$9*SQRT($C$8)) -> 1.692113 | T61: =S61-$C$9*SQRT($C$8) -> 1.0557169 | V61: =Q61-Q62 -> 0.14157435
B62: =B48 -> 250000000 | C62: =C48 -> 272500000 | E62: =O62-O63 -> 11902856 | G62: =$E62*G48 -> 0 | H62: =$E62*H48 -> 0 | I62: =$E62*I48 -> 0 | J62: =$E62*J48 -> 11902856 | K62: =$E62*K48 -> 0 | L62: =$E62*L48 -> 0 | M62: =$E62*M48 -> 0 | O62: =$C$7*Q62-B62*EXP(-$C$10*$C$8)*R62 -> 1.3147502e+08 | Q62: =NORMSDIST(S62) -> 0.81311343 | R62: =NORMSDIST(T62) -> 0.59987819 | S62: =(LN($C$7/B62)+($C$10+$C$9*$C$9/2)*$C$8)/($C$9*SQRT($C$8)) -> 0.88942794 | T62: =S62-$C$9*SQRT($C$8) -> 0.25303184 | V62: =Q62-Q63 -> 0.038534214
B63: =B49 -> 272500000 | C63: =C49 -> 282500000 | E63: =O63-O64 -> 4943346.5 | G63: =$E63*G49 -> 0 | H63: =$E63*H49 -> 0 | I63: =$E63*I49 -> 4943346.5 | J63: =$E63*J49 -> 0 | K63: =$E63*K49 -> 0 | L63: =$E63*L49 -> 0 | M63: =$E63*M49 -> 0 | O63: =$C$7*Q63-B63*EXP(-$C$10*$C$8)*R63 -> 1.1957217e+08 | Q63: =NORMSDIST(S63) -> 0.77457922 | R63: =NORMSDIST(T63) -> 0.54681429 | S63: =(LN($C$7/B63)+($C$10+$C$9*$C$9/2)*$C$8)/($C$9*SQRT($C$8)) -> 0.75401276 | T63: =S63-$C$9*SQRT($C$8) -> 0.11761665 | V63: =Q63-Q64 -> 0.01736127
B64: =B50 -> 282500000 | C64: =C50 -> 286250000 | E64: =O64-O65 -> 1800694 | G64: =$E64*G50 -> 0 | H64: =$E64*H50 -> 1800694 | I64: =$E64*I50 -> 0 | J64: =$E64*J50 -> 0 | K64: =$E64*K50 -> 0 | L64: =$E64*L50 -> 0 | M64: =$E64*M50 -> 0 | O64: =$C$7*Q64-B64*EXP(-$C$10*$C$8)*R64 -> 1.1462882e+08 | Q64: =NORMSDIST(S64) -> 0.75721795 | R64: =NORMSDIST(T64) -> 0.52431456 | S64: =(LN($C$7/B64)+($C$10+$C$9*$C$9/2)*$C$8)/($C$9*SQRT($C$8)) -> 0.69738146 | T64: =S64-$C$9*SQRT($C$8) -> 0.060985355 | V64: =Q64-Q65 -> 0.006528774
B65: =B51 -> 286250000 | C65: =C51 -> 287250000 | E65: =O65-O66 -> 475373.31 | G65: =$E65*G51 -> 475373.31 | H65: =$E65*H51 -> 0 | I65: =$E65*I51 -> 0 | J65: =$E65*J51 -> 0 | K65: =$E65*K51 -> 0 | L65: =$E65*L51 -> 0 | M65: =$E65*M51 -> 0 | O65: =$C$7*Q65-B65*EXP(-$C$10*$C$8)*R65 -> 1.1282813e+08 | Q65: =NORMSDIST(S65) -> 0.75068918 | R65: =NORMSDIST(T65) -> 0.51605866 | S65: =(LN($C$7/B65)+($C$10+$C$9*$C$9/2)*$C$8)/($C$9*SQRT($C$8)) -> 0.67666008 | T65: =S65-$C$9*SQRT($C$8) -> 0.040263977 | V65: =Q65-Q66 -> 0.001742039
B66: =B52 -> 287250000 | C66: =C52 -> and above | E66: =O66-O67 -> 1.1235275e+08 | G66: =$E66*G52 -> 5548284.1 | H66: =$E66*H52 -> 8322426.1 | I66: =$E66*I52 -> 11096568 | J66: =$E66*J52 -> 12483639 | K66: =$E66*K52 -> 13870710 | L66: =$E66*L52 -> 16644852 | M66: =$E66*M52 -> 44386273 | O66: =$C$7*Q66-B66*EXP(-$C$10*$C$8)*R66 -> 1.1235275e+08 | Q66: =NORMSDIST(S66) -> 0.74894714 | R66: =NORMSDIST(T66) -> 0.51387406 | S66: =(LN($C$7/B66)+($C$10+$C$9*$C$9/2)*$C$8)/($C$9*SQRT($C$8)) -> 0.67118022 | T66: =S66-$C$9*SQRT($C$8) -> 0.034784117 | V66: =Q66-Q67 -> 0.74894714
E69: Fair Value (per class) | G69: =SUM(G60:G66) -> 6023657.4 | H69: =SUM(H60:H66) -> 10123120 | I69: =SUM(I60:I66) -> 16039915 | J69: =SUM(J60:J66) -> 24386495 | K69: =SUM(K60:K66) -> 80992213 | L69: =SUM(L60:L66) -> 1.5e+08 | M69: =SUM(M60:M66) -> 44386273
E71: Fair Value (per share) | G71: =G69/G8 -> 60.236574 | H71: =H69/H8 -> 67.487467 | I71: =I69/I8 -> 80.199573 | J71: =J69/J8 -> 108.38442 | K71: =K69/K8 -> 323.96885 | L71: =L69/L8 -> 500 | M71: =M69/M8 -> 55.482841
E73: Series Specific Volatility | G73: =$C$9*SUMPRODUCT(G46:G52,$V$60:$V$66)*($C$7/G69) -> 0.96037732 | H73: =$C$9*SUMPRODUCT(H46:H52,$V$60:$V$66)*($C$7/H69) -> 0.91497469 | I73: =$C$9*SUMPRODUCT(I46:I52,$V$60:$V$66)*($C$7/I69) -> 0.85056054 | J73: =$C$9*SUMPRODUCT(J46:J52,$V$60:$V$66)*($C$7/J69) -> 0.74577697 | K73: =$C$9*SUMPRODUCT(K46:K52,$V$60:$V$66)*($C$7/K69) -> 0.43164683 | L73: =$C$9*SUMPRODUCT(L46:L52,$V$60:$V$66)*($C$7/L69) -> 0.15561962 | M73: =$C$9*SUMPRODUCT(M46:M52,$V$60:$V$66)*($C$7/M69) -> 0.99576034
K78: Target | L78: ='2.a Capital Structure'!E7*'2.a Capital Structure'!C7 -> 150000000
K79: Diff | L79: =L69-L78 -> 0

Sheet 3.a Capital Structure
A1: class_name | B1: type | C1: sharecount | D1: seniority | E1: liquidation_preference_per_share | F1: convertible | G1: conversion_ratio | H1: participating | I1: participation_cap_multiple
A2: Series A Preferred | B2: Preferred | C2: 100000 | D2: 1 | E2: 10 | F2: TRUE | G2: 1 | H2: TRUE | I2: 2
A3: Series B Preferred | B3: Preferred | C3: 150000 | D3: 1 | E3: 25 | F3: TRUE | G3: 1 | H3: TRUE | I3: 2
A4: Series C Preferred | B4: Preferred | C4: 200000 | D4: 1 | E4: 50 | F4: TRUE | G4: 1 | H4: TRUE | I4: 3
A5: Series D Preferred | B5: Preferred | C5: 225000 | D5: 1 | E5: 100 | F5: TRUE | G5: 1 | H5: TRUE | I5: 3
A6: Common | B6: Common | C6: 800000

Sheet 3.b OPM
B5: Inputs & Assumptions | G5: Series A Preferred | H5: Series B Preferred | I5: Series C Preferred | J5: Series D Preferred | K5: Common
B7: Equity Value | C7: 750000000 | G7: ='3.a Capital Structure'!D2 -> 1 | H7: ='3.a Capital Structure'!D3 -> 1 | I7: ='3.a Capital Structure'!D4 -> 1 | J7: ='3.a Capital Structure'!D5 -> 1 | L7: Priority
B8: T | C8: 2 | G8: ='3.a Capital Structure'!C2 -> 100000 | H8: ='3.a Capital Structure'!C3 -> 150000 | I8: ='3.a Capital Structure'!C4 -> 200000 | J8: ='3.a Capital Structure'!C5 -> 225000 | K8: ='3.a Capital Structure'!C6 -> 800000 | L8: Sharecount
B9: Volatility | C9: 0.45 | G9: ='3.a Capital Structure'!E2 -> 10 | H9: ='3.a Capital Structure'!E3 -> 25 | I9: ='3.a Capital Structure'!E4 -> 50 | J9: ='3.a Capital Structure'!E5 -> 100 | L9: Liquidation Preference (per share)
B10: Risk-free Rate | C10: 0.04 | G10: =G8*G9 -> 1000000 | H10: =H8*H9 -> 3750000 | I10: =I8*I9 -> 10000000 | J10: =J8*J9 -> 22500000 | L10: Liquidation Preference (total)
G11: ='3.a Capital Structure'!I2 -> 2 | H11: ='3.a Capital Structure'!I3 -> 2 | I11: ='3.a Capital Structure'!I4 -> 3 | J11: ='3.a Capital Structure'!I5 -> 3 | L11: Participation Cap Multiple
G12: =(G11-1)*G9 -> 10 | H12: =(H11-1)*H9 -> 25 | I12: =(I11-1)*I9 -> 100 | J12: =(J11-1)*J9 -> 200 | L12: Cap Point
G13: =G11*G9 -> 20 | H13: =H11*H9 -> 50 | I13: =I11*I9 -> 150 | J13: =J11*J9 -> 300 | L13: Conversion Point
B18: Breakpoints
B19: From | C19: To | G19: =G5 -> Series A Preferred | H19: =H5 -> Series B Preferred | I19: =I5 -> Series C Preferred | J19: =J5 -> Series D Preferred | K19: =K5 -> Common
B21: 0 | C21: =B21+SUM(G21:J21) -> 37250000 | G21: =G10 -> 1000000 | H21: =H10 -> 3750000 | I21: =I10 -> 10000000 | J21: =J10 -> 22500000
B22: =C21 -> 37250000 | C22: =B22+(E22-E21)*SUM(G22:K22) -> 52000000 | E22: =G12 -> 10 | G22: =G$8 -> 100000 | H22: =H$8 -> 150000 | I22: =I$8 -> 200000 | J22: =J$8 -> 225000 | K22: =K$8 -> 800000
B23: =C22 -> 52000000 | C23: =B23+(E23-E22)*SUM(G23:K23) -> 65750000 | E23: =G13 -> 20 | H23: =H$8 -> 150000 | I23: =I$8 -> 200000 | J23: =J$8 -> 225000 | K23: =K$8 -> 800000
B24: =C23 -> 65750000 | C24: =B24+(E24-E23)*SUM(G24:K24) -> 73125000 | E24: =H12 -> 25 | G24: =G$8 -> 100000 | H24: =H$8 -> 150000 | I24: =I$8 -> 200000 | J24: =J$8 -> 225000 | K24: =K$8 -> 800000
B25: =C24 -> 73125000 | C25: =B25+(E25-E24)*SUM(G25:K25) -> 106250000 | E25: =H13 -> 50 | G25: =G$8 -> 100000 | I25: =I$8 -> 200000 | J25: =J$8 -> 225000 | K25: =K$8 -> 800000
B26: =C25 -> 106250000 | C26: =B26+(E26-E25)*SUM(G26:K26) -> 180000000 | E26: =I12 -> 100 | G26: =G$8 -> 100000 | H26: =H$8 -> 150000 | I26: =I$8 -> 200000 | J26: =J$8 -> 225000 | K26: =K$8 -> 800000
B27: =C26 -> 180000000 | C27: =B27+(E27-E26)*SUM(G27:K27) -> 243750000 | E27: =I13 -> 150 | G27: =G$8 -> 100000 | H27: =H$8 -> 150000 | J27: =J$8 -> 225000 | K27: =K$8 -> 800000
B28: =C27 -> 243750000 | C28: =B28+(E28-E27)*SUM(G28:K28) -> 317500000 | E28: =J12 -> 200 | G28: =G$8 -> 100000 | H28: =H$8 -> 150000 | I28: =I$8 -> 200000 | J28: =J$8 -> 225000 | K28: =K$8 -> 800000
B29: =C28 -> 317500000 | C29: =B29+(E29-E28)*SUM(G29:K29) -> 442500000 | E29: =J13 -> 300 | G29: =G$8 -> 100000 | H29: =H$8 -> 150000 | I29: =I$8 -> 200000 | K29: =K$8 -> 800000
B30: =C29 -> 442500000 | C30: and above | G30: =G$8 -> 100000 | H30: =H$8 -> 150000 | I30: =I$8 -> 200000 | J30: =J$8 -> 225000 | K30: =K$8 -> 800000
B35: Breakpoints | E35: Incremental
B36: =B19 -> From | C36: =C19 -> To | E36: Distribution
B38: =B21 -> 0 | C38: =C21 -> 37250000 | E38: =C38-B38 -> 37250000 | G38: Breakpoint 1 - Series A, Series B, Series C, Series D receives liquidation preference
B39: =B22 -> 37250000 | C39: =C22 -> 52000000 | E39: =C39-B39 -> 14750000 | G39: Breakpoint 2 - All shares receive distributions until Series A reaches participation cap
B40: =B23 -> 52000000 | C40: =C23 -> 65750000 | E40: =C40-B40 -> 13750000 | G40: Breakpoint 3 - Series B, Series C, Series D, Common receive distributions until Series A converts
B41: =B24 -> 65750000 | C41: =C24 -> 73125000 | E41: =C41-B41 -> 7375000 | G41: Breakpoint 4 - All shares receive distributions until Series B reaches participation cap
B42: =B25 -> 73125000 | C42: =C25 -> 106250000 | E42: =C42-B42 -> 33125000 | G42: Breakpoint 5 - Series A, Series C, Series D, Common receive distributions until Series B converts
B43: =B26 -> 106250000 | C43: =C26 -> 180000000 | E43: =C43-B43 -> 73750000 | G43: Breakpoint 6 - All shares receive distributions until Series C reaches participation cap
B44: =B27 -> 180000000 | C44: =C27 -> 243750000 | E44: =C44-B44 -> 63750000 | G44: Breakpoint 7 - Series A, Series B, Series D, Common receive distributions until Series C converts
B45: =B28 -> 243750000 | C45: =C28 -> 317500000 | E45: =C45-B45 -> 73750000 | G45: Breakpoint 8 - All shares receive distributions until Series D reaches participation cap
B46: =B29 -> 317500000 | C46: =C29 -> 442500000 | E46: =C46-B46 -> 125000000 | G46: Breakpoint 9 - Series A, Series B, Series C, Common receive distributions until Series D converts
B47: =B30 -> 442500000 | C47: =C30 -> and above | G47: Breakpoint 10 - All shares receive distributions pro rata
B52: Breakpoints | E52: Total
B53: =B36 -> From | C53: =C36 -> To | E53: Allocation | G53: =G19 -> Series A Preferred | H53: =H19 -> Series B Preferred | I53: =I19 -> Series C Preferred | J53: =J19 -> Series D Preferred | K53: =K19 -> Common
B55: =B38 -> 0 | C55: =C38 -> 37250000 | E55: =SUM(G55:K55) -> 1 | G55: =G21/SUM($G21:$K21) -> 0.026845638 | H55: =H21/SUM($G21:$K21) -> 0.10067114 | I55: =I21/SUM($G21:$K21) -> 0.26845638 | J55: =J21/SUM($G21:$K21) -> 0.60402685 | K55: =K21/SUM($G21:$K21) -> 0
B56: =B39 -> 37250000 | C56: =C39 -> 52000000 | E56: =SUM(G56:K56) -> 1 | G56: =G22/SUM($G22:$K22) -> 0.06779661 | H56: =H22/SUM($G22:$K22) -> 0.10169492 | I56: =I22/SUM($G22:$K22) -> 0.13559322 | J56: =J22/SUM($G22:$K22) -> 0.15254237 | K56: =K22/SUM($G22:$K22) -> 0.54237288
B57: =B40 -> 52000000 | C57: =C40 -> 65750000 | E57: =SUM(G57:K57) -> 1 | G57: =G23/SUM($G23:$K23) -> 0 | H57: =H23/SUM($G23:$K23) -> 0.10909091 | I57: =I23/SUM($G23:$K23) -> 0.14545455 | J57: =J23/SUM($G23:$K23) -> 0.16363636 | K57: =K23/SUM($G23:$K23) -> 0.58181818
B58: =B41 -> 65750000 | C58: =C41 -> 73125000 | E58: =SUM(G58:K58) -> 1 | G58: =G24/SUM($G24:$K24) -> 0.06779661 | H58: =H24/SUM($G24:$K24) -> 0.10169492 | I58: =I24/SUM($G24:$K24) -> 0.13559322 | J58: =J24/SUM($G24:$K24) -> 0.15254237 | K58: =K24/SUM($G24:$K24) -> 0.54237288
B59: =B42 -> 73125000 | C59: =C42 -> 106250000 | E59: =SUM(G59:K59) -> 1 | G59: =G25/SUM($G25:$K25) -> 0.075471698 | H59: =H25/SUM($G25:$K25) -> 0 | I59: =I25/SUM($G25:$K25) -> 0.1509434 | J59: =J25/SUM($G25:$K25) -> 0.16981132 | K59: =K25/SUM($G25:$K25) -> 0.60377358
B60: =B43 -> 106250000 | C60: =C43 -> 180000000 | E60: =SUM(G60:K60) -> 1 | G60: =G26/SUM($G26:$K26) -> 0.06779661 | H60: =H26/SUM($G26:$K26) -> 0.10169492 | I60: =I26/SUM($G26:$K26) -> 0.13559322 | J60: =J26/SUM($G26:$K26) -> 0.15254237 | K60: =K26/SUM($G26:$K26) -> 0.54237288
B61: =B44 -> 180000000 | C61: =C44 -> 243750000 | E61: =SUM(G61:K61) -> 1 | G61: =G27/SUM($G27:$K27) -> 0.078431373 | H61: =H27/SUM($G27:$K27) -> 0.11764706 | I61: =I27/SUM($G27:$K27) -> 0 | J61: =J27/SUM($G27:$K27) -> 0.17647059 | K61: =K27/SUM($G27:$K27) -> 0.62745098
B62: =B45 -> 243750000 | C62: =C45 -> 317500000 | E62: =SUM(G62:K62) -> 1 | G62: =G28/SUM($G28:$K28) -> 0.06779661 | H62: =H28/SUM($G28:$K28) -> 0.10169492 | I62: =I28/SUM($G28:$K28) -> 0.13559322 | J62: =J28/SUM($G28:$K28) -> 0.15254237 | K62: =K28/SUM($G28:$K28) -> 0.54237288
B63: =B46 -> 317500000 | C63: =C46 -> 442500000 | E63: =SUM(G63:K63) -> 1 | G63: =G29/SUM($G29:$K29) -> 0.08 | H63: =H29/SUM($G29:$K29) -> 0.12 | I63: =I29/SUM($G29:$K29) -> 0.16 | J63: =J29/SUM($G29:$K29) -> 0 | K63: =K29/SUM($G29:$K29) -> 0.64
B64: =B47 -> 442500000 | C64: =C47 -> and above | E64: =SUM(G64:K64) -> 1 | G64: =G30/SUM($G30:$K30) -> 0.06779661 | H64: =H30/SUM($G30:$K30) -> 0.10169492 | I64: =I30/SUM($G30:$K30) -> 0.13559322 | J64: =J30/SUM($G30:$K30) -> 0.15254237 | K64: =K30/SUM($G30:$K30) -> 0.54237288
B69: =B52 -> Breakpoints | C69: =C52 -> 0 | E69: Option Value | M69: Call | T69: Incremental
B70: =B53 -> From | C70: =C53 -> To | G70: =G5 -> Series A Preferred | H70: =H5 -> Series B Preferred | I70: =I5 -> Series C Preferred | J70: =J5 -> Series D Preferred | K70: =K5 -> Common | M70: Option | O70: N(d1) | P70: N(d2) | Q70: d1 | R70: d2 | T70: N(d1)
B72: =B55 -> 0 | C72: =C55 -> 37250000 | E72: =M72-M73 -> 34386072 | G72: =$E72*G55 -> 923116.03 | H72: =$E72*H55 -> 3461685.1 | I72: =$E72*I55 -> 9231160.3 | J72: =$E72*J55 -> 20770111 | K72: =$E72*K55 -> 0 | M72: =C7 -> 750000000 | O72: 1 | T72: =O72-O73 -> 1.2232216e-07
B73: =B56 -> 37250000 | C73: =C56 -> 52000000 | E73: =M73-M74 -> 13615787 | G73: =$E73*G56 -> 923104.22 | H73: =$E73*H56 -> 1384656.3 | I73: =$E73*I56 -> 1846208.4 | J73: =$E73*J56 -> 2076984.5 | K73: =$E73*K56 -> 7384833.8 | M73: =$C$7*O73-B73*EXP(-$C$10*$C$8)*P73 -> 7.1561393e+08 | O73: =NORMSDIST(Q73) -> 0.99999988 | P73: =NORMSDIST(R73) -> 0.99999699 | Q73: =(LN($C$7/B73)+($C$10+$C$9*$C$9/2)*$C$8)/($C$9*SQRT($C$8)) -> 5.1617558 | R73: =Q73-$C$9*SQRT($C$8) -> 4.5253597 | T73: =O73-O74 -> 1.6403506e-06
B74: =B57 -> 52000000 | C74: =C57 -> 65750000 | E74: =M74-M75 -> 12691889 | G74: =$E74*G57 -> 0 | H74: =$E74*H57 -> 1384569.7 | I74: =$E74*I57 -> 1846092.9 | J74: =$E74*J57 -> 2076854.6 | K74: =$E74*K57 -> 7384371.8 | M74: =$C$7*O74-B74*EXP(-$C$10*$C$8)*P74 -> 7.0199814e+08 | O74: =NORMSDIST(Q74) -> 0.99999824 | P74: =NORMSDIST(R74) -> 0.99996849 | Q74: =(LN($C$7/B74)+($C$10+$C$9*$C$9/2)*$C$8)/($C$9*SQRT($C$8)) -> 4.6375669 | R74: =Q74-$C$9*SQRT($C$8) -> 4.0011708 | T74: =O74-O75 -> 8.0591395e-06
B75: =B58 -> 65750000 | C75: =C58 -> 73125000 | E75: =M75-M76 -> 6806638.5 | G75: =$E75*G58 -> 461467.02 | H75: =$E75*H58 -> 692200.52 | I75: =$E75*I58 -> 922934.03 | J75: =$E75*J58 -> 1038300.8 | K75: =$E75*K58 -> 3691736.1 | M75: =$C$7*O75-B75*EXP(-$C$10*$C$8)*P75 -> 6.8930625e+08 | O75: =NORMSDIST(Q75) -> 0.99999018 | P75: =NORMSDIST(R75) -> 0.99985966 | Q75: =(LN($C$7/B75)+($C$10+$C$9*$C$9/2)*$C$8)/($C$9*SQRT($C$8)) -> 4.2689035 | R75: =Q75-$C$9*SQRT($C$8) -> 3.6325074 | T75: =O75-O76 -> 1.067097e-05
B76: =B59 -> 73125000 | C76: =C59 -> 106250000 | E76: =M76-M77 -> 30549745 | G76: =$E76*G59 -> 2305641.2 | H76: =$E76*H59 -> 0 | I76: =$E76*I59 -> 4611282.3 | J76: =$E76*J59 -> 5187692.6 | K76: =$E76*K59 -> 18445129 | M76: =$C$7*O76-B76*EXP(-$C$10*$C$8)*P76 -> 6.8249961e+08 | O76: =NORMSDIST(Q76) -> 0.99997951 | P76: =NORMSDIST(R76) -> 0.99973533 | Q76: =(LN($C$7/B76)+($C$10+$C$9*$C$9/2)*$C$8)/($C$9*SQRT($C$8)) -> 4.1018524 | R76: =Q76-$C$9*SQRT($C$8) -> 3.4654563 | T76: =O76-O77 -> 0.00019958453
B77: =B60 -> 106250000 | C77: =C60 -> 180000000 | E77: =M77-M78 -> 67465842 | G77: =$E77*G60 -> 4573955.4 | H77: =$E77*H60 -> 6860933.1 | I77: =$E77*I60 -> 9147910.8 | J77: =$E77*J60 -> 10291400 | K77: =$E77*K60 -> 36591643 | M77: =$C$7*O77-B77*EXP(-$C$10*$C$8)*P77 -> 6.5194987e+08 | O77: =NORMSDIST(Q77) -> 0.99977992 | P77: =NORMSDIST(R77) -> 0.99800127 | Q77: =(LN($C$7/B77)+($C$10+$C$9*$C$9/2)*$C$8)/($C$9*SQRT($C$8)) -> 3.5147582 | R77: =Q77-$C$9*SQRT($C$8) -> 2.8783621 | T77: =O77-O78 -> 0.0033912193
B78: =B61 -> 180000000 | C78: =C61 -> 243750000 | E78: =M78-M79 -> 56654872 | G78: =$E78*G61 -> 4443519.4 | H78: =$E78*H61 -> 6665279.1 | I78: =$E78*I61 -> 0 | J78: =$E78*J61 -> 9997918.7 | K78: =$E78*K61 -> 35548155 | M78: =$C$7*O78-B78*EXP(-$C$10*$C$8)*P78 -> 5.8448403e+08 | O78: =NORMSDIST(Q78) -> 0.9963887 | P78: =NORMSDIST(R78) -> 0.97981812 | Q78: =(LN($C$7/B78)+($C$10+$C$9*$C$9/2)*$C$8)/($C$9*SQRT($C$8)) -> 2.6864029 | R78: =Q78-$C$9*SQRT($C$8) -> 2.0500068 | T78: =O78-O79 -> 0.0099415731
B79: =B62 -> 243750000 | C79: =C62 -> 317500000 | E79: =M79-M80 -> 62023209 | G79: =$E79*G62 -> 4204963.3 | H79: =$E79*H62 -> 6307445 | I79: =$E79*I62 -> 8409926.7 | J79: =$E79*J62 -> 9461167.5 | K79: =$E79*K62 -> 33639707 | M79: =$C$7*O79-B79*EXP(-$C$10*$C$8)*P79 -> 5.2782915e+08 | O79: =NORMSDIST(Q79) -> 0.98644713 | P79: =NORMSDIST(R79) -> 0.94220951 | Q79: =(LN($C$7/B79)+($C$10+$C$9*$C$9/2)*$C$8)/($C$9*SQRT($C$8)) -> 2.2099917 | R79: =Q79-$C$9*SQRT($C$8) -> 1.5735956 | T79: =O79-O80 -> 0.022803484
B80: =B63 -> 317500000 | C80: =C63 -> 442500000 | E80: =M80-M81 -> 93316999 | G80: =$E80*G63 -> 7465359.9 | H80: =$E80*H63 -> 11198040 | I80: =$E80*I63 -> 14930720 | J80: =$E80*J63 -> 0 | K80: =$E80*K63 -> 59722879 | M80: =$C$7*O80-B80*EXP(-$C$10*$C$8)*P80 -> 4.6580594e+08 | O80: =NORMSDIST(Q80) -> 0.96364365 | P80: =NORMSDIST(R80) -> 0.87661565 | Q80: =(LN($C$7/B80)+($C$10+$C$9*$C$9/2)*$C$8)/($C$9*SQRT($C$8)) -> 1.7946298 | R80: =Q80-$C$9*SQRT($C$8) -> 1.1582337 | T80: =O80-O81 -> 0.065152527
B81: =B64 -> 442500000 | C81: =C64 -> and above | E81: =M81-M82 -> 3.7248895e+08 | G81: =$E81*G64 -> 25253488 | H81: =$E81*H64 -> 37880232 | I81: =$E81*I64 -> 50506976 | J81: =$E81*J64 -> 56820348 | K81: =$E81*K64 -> 2.020279e+08 | M81: =$C$7*O81-B81*EXP(-$C$10*$C$8)*P81 -> 3.7248895e+08 | O81: =NORMSDIST(Q81) -> 0.89849112 | P81: =NORMSDIST(R81) -> 0.73780881 | Q81: =(LN($C$7/B81)+($C$10+$C$9*$C$9/2)*$C$8)/($C$9*SQRT($C$8)) -> 1.2730008 | R81: =Q81-$C$9*SQRT($C$8) -> 0.63660469 | T81: =O81-O82 -> 0.89849112
E84: Fair Value (per class) | G84: =SUM(G72:G81) -> 50554614 | H84: =SUM(H72:H81) -> 75835040 | I84: =SUM(I72:I81) -> 1.0145321e+08 | J84: =SUM(J72:J81) -> 1.1772078e+08 | K84: =SUM(K72:K81) -> 4.0443636e+08
E86: Fair Value (per share) | G86: =G84/G8 -> 505.54614 | H86: =H84/H8 -> 505.56694 | I86: =I84/I8 -> 507.26605 | J86: =J84/J8 -> 523.20345 | K86: =K84/K8 -> 505.54545
E88: Series Specific Volatility | G88: =$C$9*SUMPRODUCT(G55:G64,$T$72:$T$81)*($C$7/G84) -> 0.45862697 | H88: =$C$9*SUMPRODUCT(H55:H64,$T$72:$T$81)*($C$7/H84) -> 0.4585115 | I88: =$C$9*SUMPRODUCT(I55:I64,$T$72:$T$81)*($C$7/I84) -> 0.45188816 | J88: =$C$9*SUMPRODUCT(J55:J64,$T$72:$T$81)*($C$7/J84) -> 0.40953092 | K88: =$C$9*SUMPRODUCT(K55:K64,$T$72:$T$81)*($C$7/K84) -> 0.45863149

Sheet 4.a Capital Structure
A1: class_name | B1: type | C1: sharecount | D1: seniority | E1: liquidation_preference_per_share | F1: convertible | G1: conversion_ratio | H1: participating | I1: participation_cap_multiple | K1: Investment Cost (per share) | L1: Liquidation Preference Multiple | M1: Conversion Price
A2: Series A Preferred | B2: Preferred | C2: 100000 | D2: 1 | E2: =K2*L2 -> 20 | F2: TRUE | G2: 1 | K2: 10 | L2: 2 | M2: 10
A3: Series B Preferred | B3: Preferred | C3: 150000 | D3: 1 | E3: =K3*L3 -> 50 | F3: TRUE | G3: 1 | K3: 25 | L3: 2 | M3: 25
A4: Series C Preferred | B4: Preferred | C4: 200000 | D4: 1 | E4: =K4*L4 -> 100 | F4: TRUE | G4: 1 | K4: 50 | L4: 2 | M4: 50
A5: Series D Preferred | B5: Preferred | C5: 225000 | D5: 1 | E5: =K5*L5 -> 200 | F5: TRUE | G5: 1 | K5: 100 | L5: 2 | M5: 100
A6: Common | B6: Common | C6: 800000

Sheet 4.b OPM
B5: Inputs & Assumptions | G5: Series A Preferred | H5: Series B Preferred | I5: Series C Preferred | J5: Series D Preferred | K5: Common
B7: Equity Value | C7: 300000000 | G7: ='4.a Capital Structure'!D2 -> 1 | H7: ='4.a Capital Structure'!D3 -> 1 | I7: ='4.a Capital Structure'!D4 -> 1 | J7: ='4.a Capital Structure'!D5 -> 1 | L7: Priority
B8: T | C8: 2 | G8: ='4.a Capital Structure'!C2 -> 100000 | H8: ='4.a Capital Structure'!C3 -> 150000 | I8: ='4.a Capital Structure'!C4 -> 200000 | J8: ='4.a Capital Structure'!C5 -> 225000 | K8: ='4.a Capital Structure'!C6 -> 800000 | L8: Sharecount
B9: Volatility | C9: 0.45 | G9: ='4.a Capital Structure'!E2 -> 20 | H9: ='4.a Capital Structure'!E3 -> 50 | I9: ='4.a Capital Structure'!E4 -> 100 | J9: ='4.a Capital Structure'!E5 -> 200 | L9: Liquidation Preference (per share)
B10: Risk-free Rate | C10: 0.04 | G10: =G8*G9 -> 2000000 | H10: =H8*H9 -> 7500000 | I10: =I8*I9 -> 20000000 | J10: =J8*J9 -> 45000000 | L10: Liquidation Preference (total)
B15: Breakpoints
B16: From | C16: To | G16: =G5 -> Series A Preferred | H16: =H5 -> Series B Preferred | I16: =I5 -> Series C Preferred | J16: =J5 -> Series D Preferred | K16: =K5 -> Common
B18: 0 | C18: =B18+SUM(G18:J18) -> 74500000 | G18: =G10 -> 2000000 | H18: =H10 -> 7500000 | I18: =I10 -> 20000000 | J18: =J10 -> 45000000
B19: =C18 -> 74500000 | C19: =B19+(E19-E18)*SUM(G19:K19) -> 90500000 | E19: =G9 -> 20 | K19: =K$8 -> 800000
B20: =C19 -> 90500000 | C20: =B20+(E20-E19)*SUM(G20:K20) -> 117500000 | E20: =H9 -> 50 | G20: =G$8 -> 100000 | K20: =K$8 -> 800000
B21: =C20 -> 117500000 | C21: =B21+(E21-E20)*SUM(G21:K21) -> 170000000 | E21: =I9 -> 100 | G21: =G$8 -> 100000 | H21: =H$8 -> 150000 | K21: =K$8 -> 800000
B22: =C21 -> 170000000 | C22: =B22+(E22-E21)*SUM(G22:K22) -> 295000000 | E22: =J9 -> 200 | G22: =G$8 -> 100000 | H22: =H$8 -> 150000 | I22: =I$8 -> 200000 | K22: =K$8 -> 800000
B23: =C22 -> 295000000 | C23: and above | G23: =G$8 -> 100000 | H23: =H$8 -> 150000 | I23: =I$8 -> 200000 | J23: =J$8 -> 225000 | K23: =K$8 -> 800000
B28: Breakpoints | E28: Incremental
B29: =B16 -> From | C29: =C16 -> To | E29: Distribution
B31: =B18 -> 0 | C31: =C18 -> 74500000 | E31: =C31-B31 -> 74500000 | G31: Breakpoint 1 - Series A, Series B, Series C, Series D receives liquidation preference
B32: =B19 -> 74500000 | C32: =C19 -> 90500000 | E32: =C32-B32 -> 16000000 | G32: Breakpoint 2 - Common receive distributions until Series A converts
B33: =B20 -> 90500000 | C33: =C20 -> 117500000 | E33: =C33-B33 -> 27000000 | G33: Breakpoint 3 - Series A, Common receive distributions until Series B converts
B34: =B21 -> 117500000 | C34: =C21 -> 170000000 | E34: =C34-B34 -> 52500000 | G34: Breakpoint 4 - Series A, Series B, Common receive distributions until Series C converts
B35: =B22 -> 170000000 | C35: =C22 -> 295000000 | E35: =C35-B35 -> 125000000 | G35: Breakpoint 5 - Series A, Series B, Series C, Common receive distributions until Series D converts
B36: =B23 -> 295000000 | C36: =C23 -> and above | G36: Breakpoint 6 - All shares receive distributions pro rata
B41: Breakpoints | E41: Total
B42: =B29 -> From | C42: =C29 -> To | E42: Allocation | G42: =G16 -> Series A Preferred | H42: =H16 -> Series B Preferred | I42: =I16 -> Series C Preferred | J42: =J16 -> Series D Preferred | K42: =K16 -> Common
B44: =B31 -> 0 | C44: =C31 -> 74500000 | E44: =SUM(G44:K44) -> 1 | G44: =G18/SUM($G18:$K18) -> 0.026845638 | H44: =H18/SUM($G18:$K18) -> 0.10067114 | I44: =I18/SUM($G18:$K18) -> 0.26845638 | J44: =J18/SUM($G18:$K18) -> 0.60402685 | K44: =K18/SUM($G18:$K18) -> 0
B45: =B32 -> 74500000 | C45: =C32 -> 90500000 | E45: =SUM(G45:K45) -> 1 | G45: =G19/SUM($G19:$K19) -> 0 | H45: =H19/SUM($G19:$K19) -> 0 | I45: =I19/SUM($G19:$K19) -> 0 | J45: =J19/SUM($G19:$K19) -> 0 | K45: =K19/SUM($G19:$K19) -> 1
B46: =B33 -> 90500000 | C46: =C33 -> 117500000 | E46: =SUM(G46:K46) -> 1 | G46: =G20/SUM($G20:$K20) -> 0.11111111 | H46: =H20/SUM($G20:$K20) -> 0 | I46: =I20/SUM($G20:$K20) -> 0 | J46: =J20/SUM($G20:$K20) -> 0 | K46: =K20/SUM($G20:$K20) -> 0.88888889
B47: =B34 -> 117500000 | C47: =C34 -> 170000000 | E47: =SUM(G47:K47) -> 1 | G47: =G21/SUM($G21:$K21) -> 0.095238095 | H47: =H21/SUM($G21:$K21) -> 0.14285714 | I47: =I21/SUM($G21:$K21) -> 0 | J47: =J21/SUM($G21:$K21) -> 0 | K47: =K21/SUM($G21:$K21) -> 0.76190476
B48: =B35 -> 170000000 | C48: =C35 -> 295000000 | E48: =SUM(G48:K48) -> 1 | G48: =G22/SUM($G22:$K22) -> 0.08 | H48: =H22/SUM($G22:$K22) -> 0.12 | I48: =I22/SUM($G22:$K22) -> 0.16 | J48: =J22/SUM($G22:$K22) -> 0 | K48: =K22/SUM($G22:$K22) -> 0.64
B49: =B36 -> 295000000 | C49: =C36 -> and above | E49: =SUM(G49:K49) -> 1 | G49: =G23/SUM($G23:$K23) -> 0.06779661 | H49: =H23/SUM($G23:$K23) -> 0.10169492 | I49: =I23/SUM($G23:$K23) -> 0.13559322 | J49: =J23/SUM($G23:$K23) -> 0.15254237 | K49: =K23/SUM($G23:$K23) -> 0.54237288
B54: =B41 -> Breakpoints | C54: =C41 -> 0 | E54: Option Value | M54: Call | T54: Incremental
B55: =B42 -> From | C55: =C42 -> To | G55: =G5 -> Series A Preferred | H55: =H5 -> Series B Preferred | I55: =I5 -> Series C Preferred | J55: =J5 -> Series D Preferred | K55: =K5 -> Common | M55: Option | O55: N(d1) | P55: N(d2) | Q55: d1 | R55: d2 | T55: N(d1)
B57: =B44 -> 0 | C57: =C44 -> 74500000 | E57: =M57-M58 -> 68464454 | G57: =$E57*G44 -> 1837971.9 | H57: =$E57*H44 -> 6892394.7 | I57: =$E57*I44 -> 18379719 | J57: =$E57*J44 -> 41354368 | K57: =$E57*K44 -> 0 | M57: =C7 -> 300000000 | O57: 1 | T57: =O57-O58 -> 0.0042346078
B58: =B45 -> 74500000 | C58: =C45 -> 90500000 | E58: =M58-M59 -> 14274858 | G58: =$E58*G45 -> 0 | H58: =$E58*H45 -> 0 | I58: =$E58*I45 -> 0 | J58: =$E58*J45 -> 0 | K58: =$E58*K45 -> 14274858 | M58: =$C$7*O58-B58*EXP(-$C$10*$C$8)*P58 -> 2.3153555e+08 | O58: =NORMSDIST(Q58) -> 0.99576539 | P58: =NORMSDIST(R58) -> 0.97705328 | Q58: =(LN($C$7/B58)+($C$10+$C$9*$C$9/2)*$C$8)/($C$9*SQRT($C$8)) -> 2.6327681 | R58: =Q58-$C$9*SQRT($C$8) -> 1.996372 | T58: =O58-O59 -> 0.0057463986
B59: =B46 -> 90500000 | C59: =C46 -> 117500000 | E59: =M59-M60 -> 23147880 | G59: =$E59*G46 -> 2571986.7 | H59: =$E59*H46 -> 0 | I59: =$E59*I46 -> 0 | J59: =$E59*J46 -> 0 | K59: =$E59*K46 -> 20575893 | M59: =$C$7*O59-B59*EXP(-$C$10*$C$8)*P59 -> 2.1726069e+08 | O59: =NORMSDIST(Q59) -> 0.99001899 | P59: =NORMSDIST(R59) -> 0.9545496 | Q59: =(LN($C$7/B59)+($C$10+$C$9*$C$9/2)*$C$8)/($C$9*SQRT($C$8)) -> 2.3270611 | R59: =Q59-$C$9*SQRT($C$8) -> 1.690665 | T59: =O59-O60 -> 0.017650657
B60: =B47 -> 117500000 | C60: =C47 -> 170000000 | E60: =M60-M61 -> 40284260 | G60: =$E60*G47 -> 3836596.2 | H60: =$E60*H47 -> 5754894.2 | I60: =$E60*I47 -> 0 | J60: =$E60*J47 -> 0 | K60: =$E60*K47 -> 30692769 | M60: =$C$7*O60-B60*EXP(-$C$10*$C$8)*P60 -> 1.9411281e+08 | O60: =NORMSDIST(Q60) -> 0.97236834 | P60: =NORMSDIST(R60) -> 0.89979846 | Q60: =(LN($C$7/B60)+($C$10+$C$9*$C$9/2)*$C$8)/($C$9*SQRT($C$8)) -> 1.9168001 | R60: =Q60-$C$9*SQRT($C$8) -> 1.280404 | T60: =O60-O61 -> 0.06307652
B61: =B48 -> 170000000 | C61: =C48 -> 295000000 | E61: =M61-M62 -> 67747311 | G61: =$E61*G48 -> 5419784.9 | H61: =$E61*H48 -> 8129677.3 | I61: =$E61*I48 -> 10839570 | J61: =$E61*J48 -> 0 | K61: =$E61*K48 -> 43358279 | M61: =$C$7*O61-B61*EXP(-$C$10*$C$8)*P61 -> 1.5382855e+08 | O61: =NORMSDIST(Q61) -> 0.90929182 | P61: =NORMSDIST(R61) -> 0.75803967 | Q61: =(LN($C$7/B61)+($C$10+$C$9*$C$9/2)*$C$8)/($C$9*SQRT($C$8)) -> 1.3364067 | R61: =Q61-$C$9*SQRT($C$8) -> 0.70001063 | T61: =O61-O62 -> 0.22835654
B62: =B49 -> 295000000 | C62: =C49 -> and above | E62: =M62-M63 -> 86081237 | G62: =$E62*G49 -> 5836016.1 | H62: =$E62*H49 -> 8754024.1 | I62: =$E62*I49 -> 11672032 | J62: =$E62*J49 -> 13131036 | K62: =$E62*K49 -> 46688129 | M62: =$C$7*O62-B62*EXP(-$C$10*$C$8)*P62 -> 86081237 | O62: =NORMSDIST(Q62) -> 0.68093528 | P62: =NORMSDIST(R62) -> 0.43404686 | Q62: =(LN($C$7/B62)+($C$10+$C$9*$C$9/2)*$C$8)/($C$9*SQRT($C$8)) -> 0.47031576 | R62: =Q62-$C$9*SQRT($C$8) -> -0.16608034 | T62: =O62-O63 -> 0.68093528
E65: Fair Value (per class) | G65: =SUM(G57:G62) -> 19502356 | H65: =SUM(H57:H62) -> 29530990 | I65: =SUM(I57:I62) -> 40891321 | J65: =SUM(J57:J62) -> 54485404 | K65: =SUM(K57:K62) -> 1.5558993e+08
E67: Fair Value (per share) | G67: =G65/G8 -> 195.02356 | H67: =H65/H8 -> 196.87327 | I67: =I65/I8 -> 204.45661 | J67: =J65/J8 -> 242.15735 | K67: =K65/K8 -> 194.48741
E69: Series Specific Volatility | G69: =$C$9*SUMPRODUCT(G44:G49,$T$57:$T$62)*($C$7/G65) -> 0.50197168 | H69: =$C$9*SUMPRODUCT(H44:H49,$T$57:$T$62)*($C$7/H65) -> 0.48497649 | I69: =$C$9*SUMPRODUCT(I44:I49,$T$57:$T$62)*($C$7/I65) -> 0.42919983 | J69: =$C$9*SUMPRODUCT(J44:J49,$T$57:$T$62)*($C$7/J65) -> 0.26370283 | K69: =$C$9*SUMPRODUCT(K44:K49,$T$57:$T$62)*($C$7/K65) -> 0.50755233

Sheet 5.a Capital Structure
A1: class_name | B1: type | C1: sharecount | D1: seniority | E1: liquidation_preference_per_share | F1: convertible | G1: conversion_ratio | H1: participating | I1: participation_cap_multiple | K1: Liquidation Preference (per share) | L1: Preferred Dividend | M1: Issue Date | N1: Accrued Liquidation Preference | O1: Conversion Price
A2: Series A Preferred | B2: Preferred | C2: 100000 | D2: 1 | E2: =N2 -> 15.266441 | F2: TRUE | G2: =N2/O2 -> 1.5266441 | K2: 10 | L2: 0.08 | M2: 43831 | N2: =K2*(1+L2)^YEARFRAC(M2,"6/30/2025") -> 15.266441 | O2: 10
A3: Series B Preferred | B3: Preferred | C3: 150000 | D3: 1 | E3: =N3 -> 34.012224 | F3: TRUE | G3: =N3/O3 -> 1.360489 | K3: 25 | L3: 0.08 | M3: 44377 | N3: =K3*(1+L3)^YEARFRAC(M3,"6/30/2025") -> 34.012224 | O3: 25
A4: Series C Preferred | B4: Preferred | C4: 200000 | D4: 1 | E4: =N4 -> 61.785324 | F4: TRUE | G4: =N4/O4 -> 1.2357065 | K4: 50 | L4: 0.08 | M4: 44834 | N4: =K4*(1+L4)^YEARFRAC(M4,"6/30/2025") -> 61.785324 | O4: 50
A5: Series D Preferred | B5: Preferred | C5: 225000 | D5: 1 | E5: =N5 -> 103.92305 | F5: TRUE | G5: =N5/O5 -> 1.0392305 | K5: 100 | L5: 0.08 | M5: 45657 | N5: =K5*(1+L5)^YEARFRAC(M5,"6/30/2025") -> 103.92305 | O5: 100
A6: Common | B6: Common | C6: 800000

Sheet 5.b OPM
B5: Inputs & Assumptions | G5: Series A Preferred | H5: Series B Preferred | I5: Series C Preferred | J5: Series D Preferred | K5: Common
B7: Equity Value | C7: 120000000 | G7: ='5.a Capital Structure'!D2 -> 1 | H7: ='5.a Capital Structure'!D3 -> 1 | I7: ='5.a Capital Structure'!D4 -> 1 | J7: ='5.a Capital Structure'!D5 -> 1 | L7: Priority
B8: T | C8: 2 | G8: ='5.a Capital Structure'!C2 -> 100000 | H8: ='5.a Capital Structure'!C3 -> 150000 | I8: ='5.a Capital Structure'!C4 -> 200000 | J8: ='5.a Capital Structure'!C5 -> 225000 | K8: ='5.a Capital Structure'!C6 -> 800000 | L8: Sharecount
B9: Volatility | C9: 0.45 | G9: ='5.a Capital Structure'!E2 -> 15.266441 | H9: ='5.a Capital Structure'!E3 -> 34.012224 | I9: ='5.a Capital Structure'!E4 -> 61.785324 | J9: ='5.a Capital Structure'!E5 -> 103.92305 | L9: Liquidation Preference (per share)
B10: Risk-free Rate | C10: 0.04 | G10: =G8*G9 -> 1526644.1 | H10: =H8*H9 -> 5101833.6 | I10: =I8*I9 -> 12357065 | J10: =J8*J9 -> 23382686 | L10: Liquidation Preference (total)
G11: ='5.a Capital Structure'!G2 -> 1.5266441 | H11: ='5.a Capital Structure'!G3 -> 1.360489 | I11: ='5.a Capital Structure'!G4 -> 1.2357065 | J11: ='5.a Capital Structure'!G5 -> 1.0392305 | L11: Conversion Ratio
G12: =G9/G11 -> 10 | H12: =H9/H11 -> 25 | I12: =I9/I11 -> 50 | J12: =J9/J11 -> 100 | L12: Conversion Point
B18: Breakpoints
B19: From | C19: To | G19: =G5 -> Series A Preferred | H19: =H5 -> Series B Preferred | I19: =I5 -> Series C Preferred | J19: =J5 -> Series D Preferred | K19: =K5 -> Common
B21: 0 | C21: =B21+SUM(G21:J21) -> 42368229 | G21: =G10 -> 1526644.1 | H21: =H10 -> 5101833.6 | I21: =I10 -> 12357065 | J21: =J10 -> 23382686
B22: =C21 -> 42368229 | C22: =B22+(E22-E21)*SUM(G22:K22) -> 50368229 | E22: =G12 -> 10 | K22: =K$8 -> 800000
B23: =C22 -> 50368229 | C23: =B23+(E23-E22)*SUM(G23:K23) -> 63868229 | E23: =H12 -> 25 | G23: =G$8 -> 100000 | K23: =K$8 -> 800000
B24: =C23 -> 63868229 | C24: =B24+(E24-E23)*SUM(G24:K24) -> 90118229 | E24: =I12 -> 50 | G24: =G$8 -> 100000 | H24: =H$8 -> 150000 | K24: =K$8 -> 800000
B25: =C24 -> 90118229 | C25: =B25+(E25-E24)*SUM(G25:K25) -> 1.5261823e+08 | E25: =J12 -> 100 | G25: =G$8 -> 100000 | H25: =H$8 -> 150000 | I25: =I$8 -> 200000 | K25: =K$8 -> 800000
B26: =C25 -> 1.5261823e+08 | C26: and above | G26: =G$8 -> 100000 | H26: =H$8 -> 150000 | I26: =I$8 -> 200000 | J26: =J$8 -> 225000 | K26: =K$8 -> 800000
B31: Breakpoints | E31: Incremental
B32: =B19 -> From | C32: =C19 -> To | E32: Distribution
B34: =B21 -> 0 | C34: =C21 -> 42368229 | E34: =C34-B34 -> 42368229 | G34: Breakpoint 1 - Series A, Series B, Series C, Series D receives liquidation preference
B35: =B22 -> 42368229 | C35: =C22 -> 50368229 | E35: =C35-B35 -> 8000000 | G35: Breakpoint 2 - Common receive distributions until Series A converts
B36: =B23 -> 50368229 | C36: =C23 -> 63868229 | E36: =C36-B36 -> 13500000 | G36: Breakpoint 3 - Series A, Common receive distributions until Series B converts
B37: =B24 -> 63868229 | C37: =C24 -> 90118229 | E37: =C37-B37 -> 26250000 | G37: Breakpoint 4 - Series A, Series B, Common receive distributions until Series C converts
B38: =B25 -> 90118229 | C38: =C25 -> 1.5261823e+08 | E38: =C38-B38 -> 62500000 | G38: Breakpoint 5 - Series A, Series B, Series C, Common receive distributions until Series D converts
B39: =B26 -> 1.5261823e+08 | C39: =C26 -> and above | G39: Breakpoint 6 - All shares receive distributions pro rata
B44: Breakpoints | E44: Total
B45: =B32 -> From | C45: =C32 -> To | E45: Allocation | G45: =G19 -> Series A Preferred | H45: =H19 -> Series B Preferred | I45: =I19 -> Series C Preferred | J45: =J19 -> Series D Preferred | K45: =K19 -> Common
B47: =B34 -> 0 | C47: =C34 -> 42368229 | E47: =SUM(G47:K47) -> 1 | G47: =G21/SUM($G21:$K21) -> 0.036032758 | H47: =H21/SUM($G21:$K21) -> 0.1204165 | I47: =I21/SUM($G21:$K21) -> 0.29165876 | J47: =J21/SUM($G21:$K21) -> 0.55189199 | K47: =K21/SUM($G21:$K21) -> 0
B48: =B35 -> 42368229 | C48: =C35 -> 50368229 | E48: =SUM(G48:K48) -> 1 | G48: =G22/SUM($G22:$K22) -> 0 | H48: =H22/SUM($G22:$K22) -> 0 | I48: =I22/SUM($G22:$K22) -> 0 | J48: =J22/SUM($G22:$K22) -> 0 | K48: =K22/SUM($G22:$K22) -> 1
B49: =B36 -> 50368229 | C49: =C36 -> 63868229 | E49: =SUM(G49:K49) -> 1 | G49: =G23/SUM($G23:$K23) -> 0.11111111 | H49: =H23/SUM($G23:$K23) -> 0 | I49: =I23/SUM($G23:$K23) -> 0 | J49: =J23/SUM($G23:$K23) -> 0 | K49: =K23/SUM($G23:$K23) -> 0.88888889
B50: =B37 -> 63868229 | C50: =C37 -> 90118229 | E50: =SUM(G50:K50) -> 1 | G50: =G24/SUM($G24:$K24) -> 0.095238095 | H50: =H24/SUM($G24:$K24) -> 0.14285714 | I50: =I24/SUM($G24:$K24) -> 0 | J50: =J24/SUM($G24:$K24) -> 0 | K50: =K24/SUM($G24:$K24) -> 0.76190476
B51: =B38 -> 90118229 | C51: =C38 -> 1.5261823e+08 | E51: =SUM(G51:K51) -> 1 | G51: =G25/SUM($G25:$K25) -> 0.08 | H51: =H25/SUM($G25:$K25) -> 0.12 | I51: =I25/SUM($G25:$K25) -> 0.16 | J51: =J25/SUM($G25:$K25) -> 0 | K51: =K25/SUM($G25:$K25) -> 0.64
B52: =B39 -> 1.5261823e+08 | C52: =C39 -> and above | E52: =SUM(G52:K52) -> 1 | G52: =G26/SUM($G26:$K26) -> 0.06779661 | H52: =H26/SUM($G26:$K26) -> 0.10169492 | I52: =I26/SUM($G26:$K26) -> 0.13559322 | J52: =J26/SUM($G26:$K26) -> 0.15254237 | K52: =K26/SUM($G26:$K26) -> 0.54237288
B57: =B44 -> Breakpoints | C57: =C44 -> 0 | E57: Option Value | M57: Call | T57: Incremental
B58: =B45 -> From | C58: =C45 -> To | G58: =G5 -> Series A Preferred | H58: =H5 -> Series B Preferred | I58: =I5 -> Series C Preferred | J58: =J5 -> Series D Preferred | K58: =K5 -> Common | M58: Option | O58: N(d1) | P58: N(d2) | Q58: d1 | R58: d2 | T58: N(d1)
B60: =B47 -> 0 | C60: =C47 -> 42368229 | E60: =M60-M61 -> 38451506 | G60: =$E60*G47 -> 1385513.8 | H60: =$E60*H47 -> 4630195.6 | I60: =$E60*I47 -> 11214719 | J60: =$E60*J47 -> 21221078 | K60: =$E60*K47 -> 0 | M60: =C7 -> 120000000 | O60: 1 | T60: =O60-O61 -> 0.01877076
B61: =B48 -> 42368229 | C61: =C48 -> 50368229 | E61: =M61-M62 -> 6669603.7 | G61: =$E61*G48 -> 0 | H61: =$E61*H48 -> 0 | I61: =$E61*I48 -> 0 | J61: =$E61*J48 -> 0 | K61: =$E61*K48 -> 6669603.7 | M61: =$C$7*O61-B61*EXP(-$C$10*$C$8)*P61 -> 81548494 | O61: =NORMSDIST(Q61) -> 0.98122924 | P61: =NORMSDIST(R61) -> 0.92555026 | Q61: =(LN($C$7/B61)+($C$10+$C$9*$C$9/2)*$C$8)/($C$9*SQRT($C$8)) -> 2.0798257 | R61: =Q61-$C$9*SQRT($C$8) -> 1.4434296 | T61: =O61-O62 -> 0.016529189
B62: =B49 -> 50368229 | C62: =C49 -> 63868229 | E62: =M62-M63 -> 10399534 | G62: =$E62*G49 -> 1155503.8 | H62: =$E62*H49 -> 0 | I62: =$E62*I49 -> 0 | J62: =$E62*J49 -> 0 | K62: =$E62*K49 -> 9244030.2 | M62: =$C$7*O62-B62*EXP(-$C$10*$C$8)*P62 -> 74878890 | O62: =NORMSDIST(Q62) -> 0.96470005 | P62: =NORMSDIST(R62) -> 0.87933046 | Q62: =(LN($C$7/B62)+($C$10+$C$9*$C$9/2)*$C$8)/($C$9*SQRT($C$8)) -> 1.8080424 | R62: =Q62-$C$9*SQRT($C$8) -> 1.1716463 | T62: =O62-O63 -> 0.040356742
B63: =B50 -> 63868229 | C63: =C50 -> 90118229 | E63: =M63-M64 -> 16809173 | G63: =$E63*G50 -> 1600873.6 | H63: =$E63*H50 -> 2401310.4 | I63: =$E63*I50 -> 0 | J63: =$E63*J50 -> 0 | K63: =$E63*K50 -> 12806989 | M63: =$C$7*O63-B63*EXP(-$C$10*$C$8)*P63 -> 64479356 | O63: =NORMSDIST(Q63) -> 0.92434331 | P63: =NORMSDIST(R63) -> 0.78771319 | Q63: =(LN($C$7/B63)+($C$10+$C$9*$C$9/2)*$C$8)/($C$9*SQRT($C$8)) -> 1.4349078 | R63: =Q63-$C$9*SQRT($C$8) -> 0.79851166 | T63: =O63-O64 -> 0.11003319
B64: =B51 -> 90118229 | C64: =C51 -> 1.5261823e+08 | E64: =M64-M65 -> 24552833 | G64: =$E64*G51 -> 1964226.6 | H64: =$E64*H51 -> 2946339.9 | I64: =$E64*I51 -> 3928453.2 | J64: =$E64*J51 -> 0 | K64: =$E64*K51 -> 15713813 | M64: =$C$7*O64-B64*EXP(-$C$10*$C$8)*P64 -> 47670183 | O64: =NORMSDIST(Q64) -> 0.81431012 | P64: =NORMSDIST(R64) -> 0.60160195 | Q64: =(LN($C$7/B64)+($C$10+$C$9*$C$9/2)*$C$8)/($C$9*SQRT($C$8)) -> 0.89389184 | R64: =Q64-$C$9*SQRT($C$8) -> 0.25749574 | T64: =O64-O65 -> 0.28796773
B65: =B52 -> 1.5261823e+08 | C65: =C52 -> and above | E65: =M65-M66 -> 23117350 | G65: =$E65*G52 -> 1567278 | H65: =$E65*H52 -> 2350917 | I65: =$E65*I52 -> 3134556 | J65: =$E65*J52 -> 3526375.5 | K65: =$E65*K52 -> 12538224 | M65: =$C$7*O65-B65*EXP(-$C$10*$C$8)*P65 -> 23117350 | O65: =NORMSDIST(Q65) -> 0.52634238 | P65: =NORMSDIST(R65) -> 0.28423119 | Q65: =(LN($C$7/B65)+($C$10+$C$9*$C$9/2)*$C$8)/($C$9*SQRT($C$8)) -> 0.066078623 | R65: =Q65-$C$9*SQRT($C$8) -> -0.57031748 | T65: =O65-O66 -> 0.52634238
E68: Fair Value (per class) | G68: =SUM(G60:G65) -> 7673395.8 | H68: =SUM(H60:H65) -> 12328763 | I68: =SUM(I60:I65) -> 18277728 | J68: =SUM(J60:J65) -> 24747454 | K68: =SUM(K60:K65) -> 56972660
E70: Fair Value (per share) | G70: =G68/G8 -> 76.733958 | H70: =H68/H8 -> 82.191753 | I70: =I68/I8 -> 91.388639 | J70: =J68/J8 -> 109.98868 | K70: =K68/K8 -> 71.215825
E72: Series Specific Volatility | G72: =$C$9*SUMPRODUCT(G47:G52,$T$60:$T$65)*($C$7/G68) -> 0.5233039 | H72: =$C$9*SUMPRODUCT(H47:H52,$T$60:$T$65)*($C$7/H68) -> 0.46455088 | I72: =$C$9*SUMPRODUCT(I47:I52,$T$60:$T$65)*($C$7/I68) -> 0.36315069 | J72: =$C$9*SUMPRODUCT(J47:J52,$T$60:$T$65)*($C$7/J68) -> 0.19779987 | K72: =$C$9*SUMPRODUCT(K47:K52,$T$60:$T$65)*($C$7/K68) -> 0.5743901

Sheet 6.a Capital Structure
A1: class_name | B1: type | C1: sharecount | D1: seniority | E1: liquidation_preference_per_share | F1: convertible | G1: conversion_ratio | H1: participating | I1: participation_cap_multiple | K1: Liquidation Preference (per share) | L1: Preferred Dividend | M1: Issue Date | N1: Accrued Liquidation Preference | O1: Conversion Price
A2: Series A Preferred | B2: Preferred | C2: 100000 | D2: 1 | E2: =N2 -> 15.266441 | F2: TRUE | G2: =K2/O2 -> 1 | K2: 10 | L2: 0.08 | M2: 43831 | N2: =K2*(1+L2)^YEARFRAC(M2,"6/30/2025") -> 15.266441 | O2: 10
A3: Series B Preferred | B3: Preferred | C3: 150000 | D3: 1 | E3: =N3 -> 34.012224 | F3: TRUE | G3: =K3/O3 -> 1 | K3: 25 | L3: 0.08 | M3: 44377 | N3: =K3*(1+L3)^YEARFRAC(M3,"6/30/2025") -> 34.012224 | O3: 25
A4: Series C Preferred | B4: Preferred | C4: 200000 | D4: 1 | E4: =N4 -> 61.785324 | F4: TRUE | G4: =K4/O4 -> 1 | K4: 50 | L4: 0.08 | M4: 44834 | N4: =K4*(1+L4)^YEARFRAC(M4,"6/30/2025") -> 61.785324 | O4: 50
A5: Series D Preferred | B5: Preferred | C5: 225000 | D5: 1 | E5: =N5 -> 103.92305 | F5: TRUE | G5: =K5/O5 -> 1 | K5: 100 | L5: 0.08 | M5: 45657 | N5: =K5*(1+L5)^YEARFRAC(M5,"6/30/2025") -> 103.92305 | O5: 100
A6: Common | B6: Common | C6: 800000

Sheet 6.b OPM
B5: Inputs & Assumptions | G5: Series A Preferred | H5: Series B Preferred | I5: Series C Preferred | J5: Series D Preferred | K5: Common
B7: Equity Value | C7: 120000000 | G7: ='6.a Capital Structure'!D2 -> 1 | H7: ='6.a Capital Structure'!D3 -> 1 | I7: ='6.a Capital Structure'!D4 -> 1 | J7: ='6.a Capital Structure'!D5 -> 1 | L7: Priority
B8: T | C8: 2 | G8: ='6.a Capital Structure'!C2 -> 100000 | H8: ='6.a Capital Structure'!C3 -> 150000 | I8: ='6.a Capital Structure'!C4 -> 200000 | J8: ='6.a Capital Structure'!C5 -> 225000 | K8: ='6.a Capital Structure'!C6 -> 800000 | L8: Sharecount
B9: Volatility | C9: 0.45 | G9: ='6.a Capital Structure'!E2 -> 15.266441 | H9: ='6.a Capital Structure'!E3 -> 34.012224 | I9: ='6.a Capital Structure'!E4 -> 61.785324 | J9: ='6.a Capital Structure'!E5 -> 103.92305 | L9: Liquidation Preference (per share)
B10: Risk-free Rate | C10: 0.04 | G10: =G8*G9 -> 1526644.1 | H10: =H8*H9 -> 5101833.6 | I10: =I8*I9 -> 12357065 | J10: =J8*J9 -> 23382686 | L10: Liquidation Preference (total)
G11: ='6.a Capital Structure'!G2 -> 1 | H11: ='6.a Capital Structure'!G3 -> 1 | I11: ='6.a Capital Structure'!G4 -> 1 | J11: ='6.a Capital Structure'!G5 -> 1 | L11: Conversion Ratio
G12: =G9/G11 -> 15.266441 | H12: =H9/H11 -> 34.012224 | I12: =I9/I11 -> 61.785324 | J12: =J9/J11 -> 103.92305 | L12: Conversion Point
B18: Breakpoints
B19: From | C19: To | G19: =G5 -> Series A Preferred | H19: =H5 -> Series B Preferred | I19: =I5 -> Series C Preferred | J19: =J5 -> Series D Preferred | K19: =K5 -> Common
B21: 0 | C21: =B21+SUM(G21:J21) -> 42368229 | G21: =G10 -> 1526644.1 | H21: =H10 -> 5101833.6 | I21: =I10 -> 12357065 | J21: =J10 -> 23382686
B22: =C21 -> 42368229 | C22: =B22+(E22-E21)*SUM(G22:K22) -> 54581382 | E22: =G12 -> 15.266441 | K22: =K$8 -> 800000
B23: =C22 -> 54581382 | C23: =B23+(E23-E22)*SUM(G23:K23) -> 71452586 | E23: =H12 -> 34.012224 | G23: =G$8 -> 100000 | K23: =K$8 -> 800000
B24: =C23 -> 71452586 | C24: =B24+(E24-E23)*SUM(G24:K24) -> 1.0061434e+08 | E24: =I12 -> 61.785324 | G24: =G$8 -> 100000 | H24: =H$8 -> 150000 | K24: =K$8 -> 800000
B25: =C24 -> 1.0061434e+08 | C25: =B25+(E25-E24)*SUM(G25:K25) -> 1.532865e+08 | E25: =J12 -> 103.92305 | G25: =G$8 -> 100000 | H25: =H$8 -> 150000 | I25: =I$8 -> 200000 | K25: =K$8 -> 800000
B26: =C25 -> 1.532865e+08 | C26: and above | G26: =G$8 -> 100000 | H26: =H$8 -> 150000 | I26: =I$8 -> 200000 | J26: =J$8 -> 225000 | K26: =K$8 -> 800000
B31: Breakpoints | E31: Incremental
B32: =B19 -> From | C32: =C19 -> To | E32: Distribution
B34: =B21 -> 0 | C34: =C21 -> 42368229 | E34: =C34-B34 -> 42368229 | G34: Breakpoint 1 - Series A, Series B, Series C, Series D receives liquidation preference
B35: =B22 -> 42368229 | C35: =C22 -> 54581382 | E35: =C35-B35 -> 12213153 | G35: Breakpoint 2 - Common receive distributions until Series A converts
B36: =B23 -> 54581382 | C36: =C23 -> 71452586 | E36: =C36-B36 -> 16871204 | G36: Breakpoint 3 - Series A, Common receive distributions until Series B converts
B37: =B24 -> 71452586 | C37: =C24 -> 1.0061434e+08 | E37: =C37-B37 -> 29161756 | G37: Breakpoint 4 - Series A, Series B, Common receive distributions until Series C converts
B38: =B25 -> 1.0061434e+08 | C38: =C25 -> 1.532865e+08 | E38: =C38-B38 -> 52672155 | G38: Breakpoint 5 - Series A, Series B, Series C, Common receive distributions until Series D converts
B39: =B26 -> 1.532865e+08 | C39: =C26 -> and above | G39: Breakpoint 6 - All shares receive distributions pro rata
B44: Breakpoints | E44: Total
B45: =B32 -> From | C45: =C32 -> To | E45: Allocation | G45: =G19 -> Series A Preferred | H45: =H19 -> Series B Preferred | I45: =I19 -> Series C Preferred | J45: =J19 -> Series D Preferred | K45: =K19 -> Common
B47: =B34 -> 0 | C47: =C34 -> 42368229 | E47: =SUM(G47:K47) -> 1 | G47: =G21/SUM($G21:$K21) -> 0.036032758 | H47: =H21/SUM($G21:$K21) -> 0.1204165 | I47: =I21/SUM($G21:$K21) -> 0.29165876 | J47: =J21/SUM($G21:$K21) -> 0.55189199 | K47: =K21/SUM($G21:$K21) -> 0
B48: =B35 -> 42368229 | C48: =C35 -> 54581382 | E48: =SUM(G48:K48) -> 1 | G48: =G22/SUM($G22:$K22) -> 0 | H48: =H22/SUM($G22:$K22) -> 0 | I48: =I22/SUM($G22:$K22) -> 0 | J48: =J22/SUM($G22:$K22) -> 0 | K48: =K22/SUM($G22:$K22) -> 1
B49: =B36 -> 54581382 | C49: =C36 -> 71452586 | E49: =SUM(G49:K49) -> 1 | G49: =G23/SUM($G23:$K23) -> 0.11111111 | H49: =H23/SUM($G23:$K23) -> 0 | I49: =I23/SUM($G23:$K23) -> 0 | J49: =J23/SUM($G23:$K23) -> 0 | K49: =K23/SUM($G23:$K23) -> 0.88888889
B50: =B37 -> 71452586 | C50: =C37 -> 1.0061434e+08 | E50: =SUM(G50:K50) -> 1 | G50: =G24/SUM($G24:$K24) -> 0.095238095 | H50: =H24/SUM($G24:$K24) -> 0.14285714 | I50: =I24/SUM($G24:$K24) -> 0 | J50: =J24/SUM($G24:$K24) -> 0 | K50: =K24/SUM($G24:$K24) -> 0.76190476
B51: =B38 -> 1.0061434e+08 | C51: =C38 -> 1.532865e+08 | E51: =SUM(G51:K51) -> 1 | G51: =G25/SUM($G25:$K25) -> 0.08 | H51: =H25/SUM($G25:$K25) -> 0.12 | I51: =I25/SUM($G25:$K25) -> 0.16 | J51: =J25/SUM($G25:$K25) -> 0 | K51: =K25/SUM($G25:$K25) -> 0.64
B52: =B39 -> 1.532865e+08 | C52: =C39 -> and above | E52: =SUM(G52:K52) -> 1 | G52: =G26/SUM($G26:$K26) -> 0.06779661 | H52: =H26/SUM($G26:$K26) -> 0.10169492 | I52: =I26/SUM($G26:$K26) -> 0.13559322 | J52: =J26/SUM($G26:$K26) -> 0.15254237 | K52: =K26/SUM($G26:$K26) -> 0.54237288
B57: =B44 -> Breakpoints | C57: =C44 -> 0 | E57: Option Value | M57: Call | T57: Incremental
B58: =B45 -> From | C58: =C45 -> To | G58: =G5 -> Series A Preferred | H58: =H5 -> Series B Preferred | I58: =I5 -> Series C Preferred | J58: =J5 -> Series D Preferred | K58: =K5 -> Common | M58: Option | O58: N(d1) | P58: N(d2) | Q58: d1 | R58: d2 | T58: N(d1)
B60: =B47 -> 0 | C60: =C47 -> 42368229 | E60: =M60-M61 -> 38451506 | G60: =$E60*G47 -> 1385513.8 | H60: =$E60*H47 -> 4630195.6 | I60: =$E60*I47 -> 11214719 | J60: =$E60*J47 -> 21221078 | K60: =$E60*K47 -> 0 | M60: =C7 -> 120000000 | O60: 1 | T60: =O60-O61 -> 0.01877076
B61: =B48 -> 42368229 | C61: =C48 -> 54581382 | E61: =M61-M62 -> 10037065 | G61: =$E61*G48 -> 0 | H61: =$E61*H48 -> 0 | I61: =$E61*I48 -> 0 | J61: =$E61*J48 -> 0 | K61: =$E61*K48 -> 10037065 | M61: =$C$7*O61-B61*EXP(-$C$10*$C$8)*P61 -> 81548494 | O61: =NORMSDIST(Q61) -> 0.98122924 | P61: =NORMSDIST(R61) -> 0.92555026 | Q61: =(LN($C$7/B61)+($C$10+$C$9*$C$9/2)*$C$8)/($C$9*SQRT($C$8)) -> 2.0798257 | R61: =Q61-$C$9*SQRT($C$8) -> 1.4434296 | T61: =O61-O62 -> 0.027531843
B62: =B49 -> 54581382 | C62: =C49 -> 71452586 | E62: =M62-M63 -> 12356242 | G62: =$E62*G49 -> 1372915.7 | H62: =$E62*H49 -> 0 | I62: =$E62*I49 -> 0 | J62: =$E62*J49 -> 0 | K62: =$E62*K49 -> 10983326 | M62: =$C$7*O62-B62*EXP(-$C$10*$C$8)*P62 -> 71511429 | O62: =NORMSDIST(Q62) -> 0.9536974 | P62: =NORMSDIST(R62) -> 0.85208472 | Q62: =(LN($C$7/B62)+($C$10+$C$9*$C$9/2)*$C$8)/($C$9*SQRT($C$8)) -> 1.6818125 | R62: =Q62-$C$9*SQRT($C$8) -> 1.0454164 | T62: =O62-O63 -> 0.057787799
B63: =B50 -> 71452586 | C63: =C50 -> 1.0061434e+08 | E63: =M63-M64 -> 16980243 | G63: =$E63*G50 -> 1617166 | H63: =$E63*H50 -> 2425749 | I63: =$E63*I50 -> 0 | J63: =$E63*J50 -> 0 | K63: =$E63*K50 -> 12937328 | M63: =$C$7*O63-B63*EXP(-$C$10*$C$8)*P63 -> 59155187 | O63: =NORMSDIST(Q63) -> 0.8959096 | P63: =NORMSDIST(R63) -> 0.73309068 | Q63: =(LN($C$7/B63)+($C$10+$C$9*$C$9/2)*$C$8)/($C$9*SQRT($C$8)) -> 1.2585835 | R63: =Q63-$C$9*SQRT($C$8) -> 0.62218741 | T63: =O63-O64 -> 0.13143429
B64: =B51 -> 1.0061434e+08 | C64: =C51 -> 1.532865e+08 | E64: =M64-M65 -> 19232215 | G64: =$E64*G51 -> 1538577.2 | H64: =$E64*H51 -> 2307865.8 | I64: =$E64*I51 -> 3077154.4 | J64: =$E64*J51 -> 0 | K64: =$E64*K51 -> 12308618 | M64: =$C$7*O64-B64*EXP(-$C$10*$C$8)*P64 -> 42174944 | O64: =NORMSDIST(Q64) -> 0.76447531 | P64: =NORMSDIST(R64) -> 0.53362149 | Q64: =(LN($C$7/B64)+($C$10+$C$9*$C$9/2)*$C$8)/($C$9*SQRT($C$8)) -> 0.7207727 | R64: =Q64-$C$9*SQRT($C$8) -> 0.084376594 | T64: =O64-O65 -> 0.24086646
B65: =B52 -> 1.532865e+08 | C65: =C52 -> and above | E65: =M65-M66 -> 22942729 | G65: =$E65*G52 -> 1555439.2 | H65: =$E65*H52 -> 2333158.9 | I65: =$E65*I52 -> 3110878.5 | J65: =$E65*J52 -> 3499738.3 | K65: =$E65*K52 -> 12443514 | M65: =$C$7*O65-B65*EXP(-$C$10*$C$8)*P65 -> 22942729 | O65: =NORMSDIST(Q65) -> 0.52360885 | P65: =NORMSDIST(R65) -> 0.28190795 | Q65: =(LN($C$7/B65)+($C$10+$C$9*$C$9/2)*$C$8)/($C$9*SQRT($C$8)) -> 0.059213195 | R65: =Q65-$C$9*SQRT($C$8) -> -0.57718291 | T65: =O65-O66 -> 0.52360885
E68: Fair Value (per class) | G68: =SUM(G60:G65) -> 7469612 | H68: =SUM(H60:H65) -> 11696969 | I68: =SUM(I60:I65) -> 17402751 | J68: =SUM(J60:J65) -> 24720817 | K68: =SUM(K60:K65) -> 58709851
E70: Fair Value (per share) | G70: =G68/G8 -> 74.69612 | H70: =H68/H8 -> 77.979795 | I70: =I68/I8 -> 87.013757 | J70: =J68/J8 -> 109.8703 | K70: =K68/K8 -> 73.387313
E72: Series Specific Volatility | G72: =$C$9*SUMPRODUCT(G47:G52,$T$60:$T$65)*($C$7/G68) -> 0.53773638 | H72: =$C$9*SUMPRODUCT(H47:H52,$T$60:$T$65)*($C$7/H68) -> 0.47638018 | I72: =$C$9*SUMPRODUCT(I47:I52,$T$60:$T$65)*($C$7/I68) -> 0.35687457 | J72: =$C$9*SUMPRODUCT(J47:J52,$T$60:$T$65)*($C$7/J68) -> 0.19710216 | K72: =$C$9*SUMPRODUCT(K47:K52,$T$60:$T$65)*($C$7/K68) -> 0.56767284
